Workbook

Sheet All Disasters
A1: Disaster Row # | B1: Name | C1: Disaster Type | D1: Begin Date | E1: End Date | F1: CPI-Adjusted Cost ($M) | G1: Unadjusted Cost ($M) | H1: Deaths | I1: States | J1: Engines | K1: # Articles Found | L1: Avg Attribution Index | M1: Contested Share
A2: 1 | B2: Southeast Winter Storm (January 2000) | C2: Winter Storm | D2: 20000121 | E2: 20000124 | F2: 1320.3 | G2: 706 | H2: 4 | I2: AL,FL,GA,KY,MS,NC,SC,TN,VA,WV | J2: 3,4,5,6,7,8,National | K2: =COUNTIF(Master!A$2:A$2428,A2) | L2: =IFERROR(AVERAGEIFS(Master!P$2:P$2428,Master!A$2:A$2428,A2,Master!O$2:O$2428,"Relevant"),"") | M2: =IFERROR(COUNTIFS(Master!A$2:A$2428,A2,Master!O$2:O$2428,"Relevant",Master!S$2:S$2428,TRUE)/COUNTIFS(Master!A$2:A$2428,A2,Master!O$2:O$2428,"Relevant"),"")
A3: 2 | B3: Southern Severe Weather (March 2000) | C3: Severe Storm | D3: 20000328 | E3: 20000329 | F3: 1269.6 | G3: 690 | H3: 0 | I3: AL,AR,FL,GA,KY,LA,MS,NC,OK,SC,TN,TX,VA | J3: 13,14,15,3,4,5,6,7,8,National | K3: =COUNTIF(Master!A$2:A$2428,A3) | L3: =IFERROR(AVERAGEIFS(Master!P$2:P$2428,Master!A$2:A$2428,A3,Master!O$2:O$2428,"Relevant"),"") | M3: =IFERROR(COUNTIFS(Master!A$2:A$2428,A3,Master!O$2:O$2428,"Relevant",Master!S$2:S$2428,TRUE)/COUNTIFS(Master!A$2:A$2428,A3,Master!O$2:O$2428,"Relevant"),"")
A4: 3 | B4: Western Fire Season (Spring-Summer 2000) | C4: Wildfire | D4: 20000301 | E4: 20000831 | F4: 1978 | G4: 1075 | H4: 0 | I4: AK,AZ,CA,CO,HI,ID,MT,NM,NV,OR,UT,WA,WY | J4: 15,16,17,18,National | K4: =COUNTIF(Master!A$2:A$2428,A4) | L4: =IFERROR(AVERAGEIFS(Master!P$2:P$2428,Master!A$2:A$2428,A4,Master!O$2:O$2428,"Relevant"),"") | M4: =IFERROR(COUNTIFS(Master!A$2:A$2428,A4,Master!O$2:O$2428,"Relevant",Master!S$2:S$2428,TRUE)/COUNTIFS(Master!A$2:A$2428,A4,Master!O$2:O$2428,"Relevant"),"")
A5: 4 | B5: South Florida Flooding (October 2000) | C5: Flooding | D5: 20001003 | E5: 20001004 | F5: 1629 | G5: 900 | H5: 3 | I5: FL | J5: 3,4,5,6,National | K5: =COUNTIF(Master!A$2:A$2428,A5) | L5: =IFERROR(AVERAGEIFS(Master!P$2:P$2428,Master!A$2:A$2428,A5,Master!O$2:O$2428,"Relevant"),"") | M5: =IFERROR(COUNTIFS(Master!A$2:A$2428,A5,Master!O$2:O$2428,"Relevant",Master!S$2:S$2428,TRUE)/COUNTIFS(Master!A$2:A$2428,A5,Master!O$2:O$2428,"Relevant"),"")
A6: 5 | B6: Western/Central/Southeast Drought/Heat Wave (Spring-Fall 2000) | C6: Drought | D6: 20000301 | E6: 20001130 | F6: 9344.8 | G6: 4997.2 | H6: 140 | I6: AK,AL,AZ,CA,CO,FL,GA,HI,IA,ID,IL,IN,KS,KY,MI,MN,MO,MS,MT,NC,ND,NE,NM,NV,OH,OK,OR,SC,SD,TN,TX,UT,VA,WA,WI,WV,WY | J6: 10,11,12,13,14,15,16,17,18,3,4,5,6,7,8,9,National | K6: =COUNTIF(Master!A$2:A$2428,A6) | L6: =IFERROR(AVERAGEIFS(Master!P$2:P$2428,Master!A$2:A$2428,A6,Master!O$2:O$2428,"Relevant"),"") | M6: =IFERROR(COUNTIFS(Master!A$2:A$2428,A6,Master!O$2:O$2428,"Relevant",Master!S$2:S$2428,TRUE)/COUNTIFS(Master!A$2:A$2428,A6,Master!O$2:O$2428,"Relevant"),"")
A7: 6 | B7: Midwest/Ohio Valley Hail and Tornadoes (April 2001) | C7: Severe Storm | D7: 20010406 | E7: 20010411 | F7: 5508.7 | G7: 3094.8 | H7: 3 | I7: IA,IL,IN,KS,KY,MI,MN,MO,ND,NE,OH,SD,TN,WI,WV | J7: 10,11,12,13,3,4,5,6,7,8,9,National | K7: =COUNTIF(Master!A$2:A$2428,A7) | L7: =IFERROR(AVERAGEIFS(Master!P$2:P$2428,Master!A$2:A$2428,A7,Master!O$2:O$2428,"Relevant"),"") | M7: =IFERROR(COUNTIFS(Master!A$2:A$2428,A7,Master!O$2:O$2428,"Relevant",Master!S$2:S$2428,TRUE)/COUNTIFS(Master!A$2:A$2428,A7,Master!O$2:O$2428,"Relevant"),"")
A8: 7 | B8: North Central Severe Weather (May 2001) | C8: Severe Storm | D8: 20010430 | E8: 20010501 | F8: 1194.3 | G8: 671 | H8: 0 | I8: IA,IL,IN,KS,MI,MN,MO,ND,NE,OH,SD,WI | J8: 10,11,12,13,8,9,National | K8: =COUNTIF(Master!A$2:A$2428,A8) | L8: =IFERROR(AVERAGEIFS(Master!P$2:P$2428,Master!A$2:A$2428,A8,Master!O$2:O$2428,"Relevant"),"") | M8: =IFERROR(COUNTIFS(Master!A$2:A$2428,A8,Master!O$2:O$2428,"Relevant",Master!S$2:S$2428,TRUE)/COUNTIFS(Master!A$2:A$2428,A8,Master!O$2:O$2428,"Relevant"),"")
A9: 8 | B9: Tropical Storm Allison (June 2001) | C9: Tropical Cyclone | D9: 20010605 | E9: 20010617 | F9: 15084 | G9: 8522 | H9: 43 | I9: LA,TX | J9: 13,14,15,National | K9: =COUNTIF(Master!A$2:A$2428,A9) | L9: =IFERROR(AVERAGEIFS(Master!P$2:P$2428,Master!A$2:A$2428,A9,Master!O$2:O$2428,"Relevant"),"") | M9: =IFERROR(COUNTIFS(Master!A$2:A$2428,A9,Master!O$2:O$2428,"Relevant",Master!S$2:S$2428,TRUE)/COUNTIFS(Master!A$2:A$2428,A9,Master!O$2:O$2428,"Relevant"),"")
A10: 9 | B10: Severe Storms and Tornadoes (April 2002) | C10: Severe Storm | D10: 20020427 | E10: 20020428 | F10: 3663.9 | G10: 2093.8 | H10: 7 | I10: NATIONAL | J10: National | K10: =COUNTIF(Master!A$2:A$2428,A10) | L10: =IFERROR(AVERAGEIFS(Master!P$2:P$2428,Master!A$2:A$2428,A10,Master!O$2:O$2428,"Relevant"),"") | M10: =IFERROR(COUNTIFS(Master!A$2:A$2428,A10,Master!O$2:O$2428,"Relevant",Master!S$2:S$2428,TRUE)/COUNTIFS(Master!A$2:A$2428,A10,Master!O$2:O$2428,"Relevant"),"")
A11: 10 | B11: Hurricane Lili (October 2002) | C11: Tropical Cyclone | D11: 20020801 | E11: 20020805 | F11: 1932.9 | G11: 1104.5 | H11: 2 | I11: LA | J11: 13,14,15,National | K11: =COUNTIF(Master!A$2:A$2428,A11) | L11: =IFERROR(AVERAGEIFS(Master!P$2:P$2428,Master!A$2:A$2428,A11,Master!O$2:O$2428,"Relevant"),"") | M11: =IFERROR(COUNTIFS(Master!A$2:A$2428,A11,Master!O$2:O$2428,"Relevant",Master!S$2:S$2428,TRUE)/COUNTIFS(Master!A$2:A$2428,A11,Master!O$2:O$2428,"Relevant"),"")
A12: 11 | B12: Tropical Storm Isidore (September 2002) | C12: Tropical Cyclone | D12: 20020925 | E12: 20020927 | F12: 2001 | G12: 1150 | H12: 5 | I12: AL,LA,MS | J12: 13,14,15,6,7,8,National | K12: =COUNTIF(Master!A$2:A$2428,A12) | L12: =IFERROR(AVERAGEIFS(Master!P$2:P$2428,Master!A$2:A$2428,A12,Master!O$2:O$2428,"Relevant"),"") | M12: =IFERROR(COUNTIFS(Master!A$2:A$2428,A12,Master!O$2:O$2428,"Relevant",Master!S$2:S$2428,TRUE)/COUNTIFS(Master!A$2:A$2428,A12,Master!O$2:O$2428,"Relevant"),"")
A13: 12 | B13: Eastern Tornadoes and Severe Storms (November 2002) | C13: Severe Storm | D13: 20021109 | E13: 20021111 | F13: 1252.8 | G13: 720 | H13: 28 | I13: CT,DE,FL,GA,MA,MD,ME,NC,NH,NJ,NY,PA,RI,SC,VA,VT,WV | J13: 1,2,3,4,5,6,National | K13: =COUNTIF(Master!A$2:A$2428,A13) | L13: =IFERROR(AVERAGEIFS(Master!P$2:P$2428,Master!A$2:A$2428,A13,Master!O$2:O$2428,"Relevant"),"") | M13: =IFERROR(COUNTIFS(Master!A$2:A$2428,A13,Master!O$2:O$2428,"Relevant",Master!S$2:S$2428,TRUE)/COUNTIFS(Master!A$2:A$2428,A13,Master!O$2:O$2428,"Relevant"),"")
... A314: 313 | B314: Southern/Eastern/Northwestern Drought and Heat Wave (2024) | C314: Drought | D314: 20240101 | E314: 20241231 | F314: 5417 | G314: 5311 | H314: 136 | I314: AL,AR,CT,DE,FL,GA,ID,KY,LA,MA,MD,ME,MS,MT,NC,NH,NJ,NY,OK,OR,PA,RI,SC,TN,TX,VA,VT,WA,WV | J314: 1,13,14,15,16,17,18,2,3,4,5,6,7,8,National | K314: =COUNTIF(Master!A$2:A$2428,A314) | L314: =IFERROR(AVERAGEIFS(Master!P$2:P$2428,Master!A$2:A$2428,A314,Master!O$2:O$2428,"Relevant"),"") | M314: =IFERROR(COUNTIFS(Master!A$2:A$2428,A314,Master!O$2:O$2428,"Relevant",Master!S$2:S$2428,TRUE)/COUNTIFS(Master!A$2:A$2428,A314,Master!O$2:O$2428,"Relevant"),"")

Sheet Master
A1: Disaster Row # | B1: Article # | C1: Name | D1: Disaster Type | E1: Begin Date | F1: End Date | G1: CPI-Adjusted Cost ($M) | H1: Unadjusted Cost ($M) | I1: Deaths | J1: States | K1: Engines | L1: URL | M1: Title | N1: Snippet | O1: Relevance | P1: Attribution Score | Q1: Attribution Category | R1: D-Subtype | S1: Contested | T1: LLM Rationale | U1: National Newspaper | V1: Calibration Sample | W1: Full Article Text | X1: Archive URL | Y1: Archive Status | Z1: Word Count | AA1: Domain | AB1: Ad Fontes Bias Score | AC1: AllSides Rating (Numeric) | AD1: Political Lean Group
A2: 1 | B2: 1 | C2: Southeast Winter Storm (January 2000) | D2: Winter Storm | E2: 20000121 | F2: 20000124 | G2: 1320.3 | H2: 706 | I2: 4 | J2: AL,FL,GA,KY,MS,NC,SC,TN,VA,WV | K2: 3,4,5,6,7,8,National | L2: https://www.nytimes.com/2000/01/24/us/500000-homes-left-dark-by-ice-storm-in-southeast.html | M2: 500000 Homes Left Dark By Ice Storm in Southeast | N2: Jan 24, 2000 ... Winter storm sweeps Southeast, from northeast Georgia to central ... 24, 2000, Section A, Page 12 of the National edition with the ... | O2: Relevant | P2: 0 | Q2: C | S2: FALSE | T2: Backfilled from Calibration sheet's LLM code -- this article was part of the 50-article human/LLM calibration sample and was intentionally skipped by the full-sample coding pass to avoid double-coding/double-cost. See Calibration sheet for the original human vs. LLM comparison and reliability stats. | U2: =IF(SUMPRODUCT(--ISNUMBER(SEARCH('National Domains'!$A$2:$A$48,L2)))>0,"Yes","No") | V2: =IF(COUNTIFS(Calibration!$A:$A,A2,Calibration!$B:$B,B2)>0,"Yes","No") | W2: ATLANTA, Jan. 23 -- A sluggish winter storm dripped a crippling coating of ice on much of the Southeast today, cracking thousands of drooping pine trees and cutting off electric power to more than 500,000 households, mostly in Atlanta. From northeast Georgia to central North Carolina, hundreds of roads were closed by fallen pines, never the sturdiest trees even in normal conditions. In urban areas, the trees generally took power lines down with them, leaving many neighborhoods in Atlanta a chaotic mix of scattered tree limbs, live wires and nonfunctioning traffic lights. ''In 18 years, this is the most ice I've ever seen accumulate,'' said Tom Moore, senior meteorologist with the Weather Channel, which is based here. ''The saving grace was that it was a Sunday morning.'' Many other Atlantans were also thankful the storm did not occur a week later, when the Super Bowl will be played at the Georgia Dome downtown. About 320,000 homes in Atlanta -- a quarter of the metropolitan area --were without power by this evening, said Lisa Frederick, a spokeswoman for Georgia Power. Atlanta is one of the most heavily forested cities in the country, and because of the large number of fallen trees, the company said it might be two days before power is restored. In some cases, lights that came back on went off again an hour later when another tree succumbed. It was the worst storm in the area since crews took a week to restore power to 570,000 customers after a blizzard in March 1993, Ms. Frederick said. Most homes in the region are heated by forced-air furnaces, which require electricity. With temperatures hovering around freezing, many people huddled near fireplaces or relied on kerosene heaters, which sold briskly at stores. Inevitably, the reliance on heaters produced a rash of house fires, the worst of which killed three people on the southwest side of the city early today. Many families lost both their power and their roofs to falling trees. Kent M. Harper arrived at his Dekalb County home this morning after his evening shift at the post office to find two large tree limbs protruding from his roof. ''It was like somebody had thrown a spear or a javelin through it,'' said Mr. Harper, a transportation supervisor, surveying the icicles building up in his living room. ''I knew I should have had those pine trees cut down.'' His family, like many others, cooked lunch in an iron skillet in the fireplace. Chain saws echoed throughout the city as people tried to move limbs covered with a half-inch of ice. Many people in the northern suburbs were trapped in their subdivisions until someone with a saw or a winch could clear an entrance road. Even walking was hazardous, as any branch could fall with a gunfire crack and a shower of ice. ''I heard an explosion, and then I ran,'' said Germaine Dozier, a receptionist who was walking in her midtown neighborhood this morning. ''This huge branch fell right where I was standing. It was like wartime or something.'' The ice coated about 40 counties in the northern third of Georgia, according to the state emergency management agency, and conditions in seven counties were serious enough that the state declared emergencies, urging motorists not to go out. Similar conditions prevailed in parts of southeastern Tennessee and western portions of the Carolinas. Mr. Moore said the ice was the result of a layer of warm air that floated atop a colder layer near the ground. Without the warmth, the rain might have turned to less damaging snow, he said. The storm extended from Alabama, where 33,000 homes and businesses were without power, to around Greensboro, N.C. North Carolina's major utilities reported approximately 20,000 customers without electricity today after parts of that state got a mixture of sleet, rain and snow. But, a Carolina Power and Light spokeswoman, Sally Ramey, said not all of the power losses could be blamed on the weather. Parts of South Carolina got up to 6 inches of snow late Saturday, and traffic on Interstate 85 came to a standstill in several spots because of slippery pavement and accidents. Hartsfield International Airport in Atlanta, the world's busiest, was open through the day, but many flights were delayed for de-icing. In central Tennessee, where 3.5 inches of snow fell on Saturday, a de-icing truck nicked the wing of a Northwest Airlines DC-9 at Nashville International Airport, The Associated Press reported. No one was injured, said a spokeswoman for Northwest, Mary Beth Schubert. -------------------- Jet Slides off Runway CHARLOTTE, N.C., Jan. 23 (AP) -- A US Airways jet skidded off the runway after landing at Charlotte-Douglas International Airport on Saturday as a storm blanketed the area with snow and freezing rain. None of the 142 passengers were hurt. A US Airways spokeswoman, Sharon Taylor, said Flight 2399, an MD-80 coming from Orlando, Fla., landed at 7:26 p.m. and was turning from the runway onto a taxiway when it slid onto a grassy area. ''Everyone was fine,'' Ms. Taylor said. ''We offloaded the passengers on mobile air stairs.'' Most of the passengers made their connecting flights, she said. | X2: http://web.archive.org/web/20251023055611/https://www.nytimes.com/2000/01/24/us/500000-homes-left-dark-by-ice-storm-in-southeast.html | Y2: found | Z2: 858 | AA2: nytimes.com | AB2: -8.02 | AC2: -2.5 | AD2: Left-leaning
A3: 3 | B3: 1 | C3: Western Fire Season (Spring-Summer 2000) | D3: Wildfire | E3: 20000301 | F3: 20000831 | G3: 1978 | H3: 1075 | I3: 0 | J3: AK,AZ,CA,CO,HI,ID,MT,NM,NV,OR,UT,WA,WY | K3: 15,16,17,18,National | L3: http://www.cnn.com/2000/US/08/13/wildfires.02/index.html | M3: Western wildfires finally lose ground - August 13, 2000 - CNN | N3: Aug 13, 2000 ... CNN.com · U.S. News ; Western wildfires finally lose ground. GALLERY. A cheatgrass fire in Nevada moves as fast as the wind will carry it -- ... | O3: Relevant | P3: 0 | Q3: C | S3: FALSE | T3: The article is clearly about the Western wildfire season of summer 2000, covering active fires across multiple affected states, costs, and federal relief efforts. There is no mention of climate change, global warming, or any other causal attribution — it is purely event reporting on fire status, impacts, and response. | U3: =IF(SUMPRODUCT(--ISNUMBER(SEARCH('National Domains'!$A$2:$A$48,L3)))>0,"Yes","No") | V3: =IF(COUNTIFS(Calibration!$A:$A,A3,Calibration!$B:$B,B3)>0,"Yes","No") | W3: HELENA, Montana (CNN) - Firefighters faced a smaller battlefield Sunday as the number of acres ablaze across the West declined slightly. Even so, federal officials have promised to cut through red tape and get immediate financial relief for fire-ravaged Montana -- one of the worst-hit states. On Sunday, the National Fire Information Center reported 76 large fires burning across 868,975 acres -- 54,560 acres less than a day earlier. Although firefighters were contending Sunday with seven additional fires, they took satisfaction in their accomplishment. "We are making progress," said Ed Waldapfel, a spokesman for the National Interagency Fire Center in Boise, Idaho. Wildfires are burning in 13 states: Idaho, Wyoming, Montana, South Dakota, Texas, New Mexico, Arizona, Utah, Nevada, Colorado, Washington, Oregon and California. Residents affected by the fire got a boost Saturday when James Lee Witt, director of the Federal Emergency Management Agency (FEMA), toured burned areas in Montana. He vowed to local and state officials that he would expedite efforts to get federal funds to the state. "They need the money now, and that's what we're going to do," Witt told CNN. To estimate the costs of the ongoing firefighting effort, officials from the emergency management agency will hold a conference call Monday with state officials and those from federal park and forestry agencies, said Matthew Furman, a spokesman for the emergency management agency, during an interview with CNN. Once the estimated cost is determined, Furman said a check will be issued within days for 50 percent of the figure; this will eliminate the need for a special session of the state legislature. In Montana alone, costs on the state, local and federal levels have surpassed $64 million. In the 13 states now battling large fires, the costs are estimated at $15 million per day, noted Waldapfel of the National Interagency Fire Center. "We just need to make sure that we can try to protect homes, and take care of families that have been affected," said Witt. "These people out here have gone through an awful ordeal." Meanwhile, cooler weather in Montana has allowed firefighters to make progress on two fires burning 12 to 15 miles south of Helena. Larry Akers of the Montana Division of Disaster and Emergency Services said a mandatory evacuation order had been lifted covering some 270 residents. Akers noted the evacuations had been ordered eight to 10 days ago. An additional 500 soldiers from the 20th Engineer Battalion, First Cavalry Division at Fort Hood, Texas, have completed their initial training and will begin training on the fire lines Sunday in Montana. South Dakota was added to the list of states battling wildfires. A 1,500 acre fire was burning on the rugged terrain of Flag Pole Mountain, near the city of Hot Springs in the state's southwestern corner. Firefighter killed, another injured as U.S. forests continue to burn August 12, 2000 Wildfires spur more Montana evacuations August 11, 2000 Army sending more troops to Western wildfire zone August 10, 2000 Now 70 large wildfires in West August 9, 2000 Exhausted firefighters return to battle after presidential praise August 8, 2000 More Army troops called to fight Western wildfires August 7, 2000 Wildfire smoke triggers health alert, may force new evacuations August 6, 2000 National Interagency Fire Center National Wildland/Urban Interface Fire Protection Program National Association of State Foresters U.S. Bureau of Land Management Firehouse.Com Idaho Large Wildland Fires Access Idaho - The Official Website of the State of Idaho State of Montana Fire Information U.S. Forest Service Note: Pages will open in a new browser window External sites are not endorsed by CNN Interactive. | X3: http://web.archive.org/web/20040901023251/http://www.cnn.com:80/2000/US/08/13/wildfires.02/index.html | Y3: found | Z3: 600 | AA3: cnn.com | AB3: -6.27 | AC3: -2.5 | AD3: Left-leaning
A4: 3 | B4: 2 | C4: Western Fire Season (Spring-Summer 2000) | D4: Wildfire | E4: 20000301 | F4: 20000831 | G4: 1978 | H4: 1075 | I4: 0 | J4: AK,AZ,CA,CO,HI,ID,MT,NM,NV,OR,UT,WA,WY | K4: 15,16,17,18,National | L4: http://www.cnn.com/2000/US/07/04/colorado.wildfires/index.html | M4: Two wildfires burn in Colorado - July 4, 2000 - CNN | N4: Jul 4, 2000 ... June 15, 2000. Wildfires rage in western United States June 14, 2000. Firefighters gain hold on Southern California wildfire. June 12, 2000 | O4: Relevant | P4: 0 | Q4: C | S4: FALSE | T4: The article directly covers two specific wildfires burning in Colorado in July 2000, which falls within the event window and affected states. It is pure event reporting — detailing acreage burned, locations, and firefighting conditions — with no discussion of climate change or any other causal framing. | U4: =IF(SUMPRODUCT(--ISNUMBER(SEARCH('National Domains'!$A$2:$A$48,L4)))>0,"Yes","No") | V4: =IF(COUNTIFS(Calibration!$A:$A,A4,Calibration!$B:$B,B4)>0,"Yes","No") | W4: CRAIG, Colorado (CNN) -- Firefighters were battling two wildfires Tuesday in remote areas of western Colorado. The fires have already consumed 11,500 acres of land and are expected to grow. Officials reported no injuries and said there were no structures immediately threatened by either blaze, both of which began Monday and are confined mostly to federal lands. The Buster Flats fire started in Dinosaur National Monument in the northwest corner of the state and moved into the nearby Diamond Breaks Wilderness Study Area and a small portion of the Brown's Park Wildlife Refuge, according to a press release from the Craig Interagency Dispatch Center. Approximately 9,000 acres have burned. To the south, the Cone Mountain fire scorched at least 2,500 acres of land some outside the city of Gateway. David Lehmann, a spokesman for the federal interagency fire center in Grand Junction, said conditions were ripe for the fire to spread. "They're about the worst we've seen," he said of the dry conditions. So far, the city of Gateway is not in any danger from the blaze, he said. Firefighters have been hampered in their efforts to contain the blazes by low humidity and high winds. Lehmann said gusts have reach 25 mph. Fire rages on nuclear reservation in Washington state June 29, 2000 One Colorado fire under control; another nearly contained June 20, 2000 Changing weather may aid crews battling Colorado wildfires June 15, 2000 Wildfires rage in western United StatesJune 14, 2000 Firefighters gain hold on Southern California wildfire June 12, 2000 Wildfires still burning in 4 U.S. states June 5, 2000 City of Craig Craig Colorado Police Department Colorado State Parks Dinosaur National Monument Cone Mountain Grand Junction Visitor and Convention Bureau Note: Pages will open in a new browser window External sites are not endorsed by CNN Interactive. | X4: https://web.archive.org/web/20260620001356/https://www.cnn.com/2000/US/07/04/colorado.wildfires/index.html | Y4: found | Z4: 302 | AA4: cnn.com | AB4: -6.27 | AC4: -2.5 | AD4: Left-leaning
A5: 3 | B5: 3 | C5: Western Fire Season (Spring-Summer 2000) | D5: Wildfire | E5: 20000301 | F5: 20000831 | G5: 1978 | H5: 1075 | I5: 0 | J5: AK,AZ,CA,CO,HI,ID,MT,NM,NV,OR,UT,WA,WY | K5: 15,16,17,18,National | L5: http://www.cnn.com/2000/US/09/12/wildfires.01/index.html | M5: West still on wildfire watch - September 12, 2000 - CNN | N5: Sep 12, 2000 ... The National Interagency Fire Center reported that several states, mostly in the West, have very high to extreme fire conditions -- Arizona, ... | O5: Borderline | S5: FALSE | T5: The article is dated September 12, 2000, just outside the event window (March–August 2000), and primarily reports on ongoing fire conditions as the season winds down, referencing the cumulative 2000 fire season acreage. It plausibly covers the tail end of the Western Fire Season event but is thin on specific event details and the date falls slightly outside the defined window. | U5: =IF(SUMPRODUCT(--ISNUMBER(SEARCH('National Domains'!$A$2:$A$48,L5)))>0,"Yes","No") | V5: =IF(COUNTIFS(Calibration!$A:$A,A5,Calibration!$B:$B,B5)>0,"Yes","No") | W5: By CNN.com Senior Writer Jim Morris BOISE, Idaho (CNN) -- Despite a dramatic drop in U.S. wildfire activity, firefighters said Tuesday their guard is still up. The National Interagency Fire Center reported that several states, mostly in the West, have very high to extreme fire conditions -- Arizona, Arkansas, California, Colorado, Idaho, Kansas, Montana, Nevada, Oklahoma, Oregon, Texas, Utah and Wyoming. On the positive side, the NIFC said rain helped firefighters contain the four remaining Texas wildfires, including the 15,864-acre (25-square-mile) Moore Branch blaze, 30 miles north of Beaumont. A week ago, there were 81 large wildfires in the United States, including 25 each in Texas and Montana. On Tuesday, the fire center reported 13 blazes in six states: • California (1 fire) • Florida (1) • Idaho (2) • Montana (7) • Nevada (1) • Wyoming (1) So far this year, wildfires throughout the United States have burned 6,649,279 acres (10,389 square miles), the fire center said Tuesday. By comparison, the land area of New Jersey is 7,418 square miles; Massachusetts is 7,838 square miles; New Hampshire is 8,969 square miles; Vermont is 9,249 square miles; and Maryland is 9,774 square miles. 'Good progress' against U.S. wildfiresSeptember 8, 2000 U.S. wildfires tamed, but not outSeptember 7, 2000 Texas takes lead in number of U.S. wildfiresSeptember 6, 2000 Wildland Fire Potential Assessment (through Oct 5) National Interagency Fire Center (NIFC) • Texas Wildland Fires 2000 Note: Pages will open in a new browser window External sites are not endorsed by CNN Interactive. | X5: http://web.archive.org/web/20040811191020/http://www.cnn.com:80/2000/US/09/12/wildfires.01/index.html | Y5: found | Z5: 252 | AA5: cnn.com | AB5: -6.27 | AC5: -2.5 | AD5: Left-leaning
A6: 3 | B6: 4 | C6: Western Fire Season (Spring-Summer 2000) | D6: Wildfire | E6: 20000301 | F6: 20000831 | G6: 1978 | H6: 1075 | I6: 0 | J6: AK,AZ,CA,CO,HI,ID,MT,NM,NV,OR,UT,WA,WY | K6: 15,16,17,18,National | L6: http://www.cnn.com/2000/NATURE/08/18/urban.interface/index.html | M6: Western wildfires often battled in the front yard - August 18, 2000 | N6: Aug 18, 2000 ... As the wildfires continue to burn in Montana's Bitteroot Valley, nearly a quarter of a million acres of the Bitteroot National Forest have ... | O6: Relevant | P6: -1 | Q6: D | R6: other_human_causes | S6: FALSE | T6: The article covers the 2000 Montana/Bitterroot Valley wildfires directly, falling within the event window and affected states. The causal framing centers entirely on the "urban interface" problem — human settlement patterns pushing homes into historically fire-prone forests — with the mayor explicitly noting these forests "have for centuries burned on a regular basis," attributing risk to land-use decisions and natural fire cycles, with no mention of climate change. | U6: =IF(SUMPRODUCT(--ISNUMBER(SEARCH('National Domains'!$A$2:$A$48,L6)))>0,"Yes","No") | V6: =IF(COUNTIFS(Calibration!$A:$A,A6,Calibration!$B:$B,B6)>0,"Yes","No") | W6: August 18, 2000 Web posted at: 3:50 PM EDT (1950 GMT) By From Rick Lockridge CNN Science Correspondent DARBY, Montana (CNN) -- As the wildfires continue to burn in Montana's Bitteroot Valley, nearly a quarter of a million acres of the Bitteroot National Forest have already burned and more than 50 homes have been destroyed. Nearly 2,000 firefighters are battling the blazes and more are on the way. Although these are forest fires, crews often find themselves working in people's front yards. In recent years, thousands of families have built homes just outside the national forest. Authorities call this meeting of residence and forest an "urban interface." "This urban interface does not deal with large communities, but it deals with a lot of homes that are scattered and that makes it even more difficult, " said Sonny Lasalle with the U.S. Forest Service. Helicopters have dropped thousands of buckets of water to keep flames away from homes and air tankers have made countless trips to coat structures with flame retardant. Twenty-man crews have been working around the clock digging fire lines and lighting backfires, to create a barrier between the blazes and the houses. "Most of the resources this past week have gone to the structure protection. We've lost some structures in the incident but we've saved quite a few more than we've lost," according to Bob Summerfield, a fire information officer with the U.S. Forest Service. "We've had engines and crews out putting the bulk of their effort into taking measures around homes, building fire lines, setting up sprinkler systems and foaming houses to protect those structures," Summerfield said. Hundreds of residents have been evacuated and special crews have moved in to try to protect the homes. But some houses nestled in the trees are impossible to protect. Firefighters say there are things people can do to make their homes more fire-resistant. "The main thing is to get some vegetation away from your house, use building materials that are less fire prone and then have a little bit of a lawn. I know we all don't like to mow grass but have a little bit of lawn or a rock garden -- something that won't burn," said Fire Information Officer Bobby Kitchens. As the flames approach their neighborhoods, some residents have resorted to hiring professional loggers to cut the trees around the homes. They've learned a lesson from the less fortunate. Darby Mayor Forest Hayes offered this insight: "Our forests are born in fire and they die in fire. Now we have homes that are back in areas that have for centuries have burned on a regular basis. This year we have a fire that's going to change the way people live in this valley. It's unfortunate, but that's the bottom line." New wildfire evacuations in West August 18, 2000 U.S. wildfires burned more than 5 million acres so far this year August 17, 2000 State of Montana declared disaster area as fires rage August 16, 2000 Wildfires ignite forest management debate August 16, 2000 Wildfires grow faster than supply of firefighters August 15, 2000 GORP - Bitterroot National Forest USDA Forest Service Note: Pages will open in a new browser window External sites are not endorsed by CNN Interactive. | X6: http://web.archive.org/web/20040822120555/http://www.cnn.com:80/2000/NATURE/08/18/urban.interface/index.html | Y6: found | Z6: 541 | AA6: cnn.com | AB6: -6.27 | AC6: -2.5 | AD6: Left-leaning
A7: 3 | B7: 5 | C7: Western Fire Season (Spring-Summer 2000) | D7: Wildfire | E7: 20000301 | F7: 20000831 | G7: 1978 | H7: 1075 | I7: 0 | J7: AK,AZ,CA,CO,HI,ID,MT,NM,NV,OR,UT,WA,WY | K7: 15,16,17,18,National | L7: http://www.cnn.com/2000/US/09/08/wildfires.02/index.html | M7: 'Good progress' against U.S. wildfires - September 8, 2000 - CNN | N7: Sep 8, 2000 ... By Jim Morris CNN.com Senior Writer. GALLERY. Click here for images of the ongoing fight against the wildfires. WEATHER FORECASTS. Idaho | O7: Borderline | S7: FALSE | T7: The article is dated September 8, 2000, which falls just outside the event window (ending August 31, 2000), and while it references the ongoing western wildfire season with cumulative acreage stats, it is primarily a brief operational update focusing on fire status in Texas and the northern Rockies rather than substantively covering the documented spring-summer 2000 western fire event. The geographic focus also skews toward Texas, which is not among the listed affected states for this event. | U7: =IF(SUMPRODUCT(--ISNUMBER(SEARCH('National Domains'!$A$2:$A$48,L7)))>0,"Yes","No") | V7: =IF(COUNTIFS(Calibration!$A:$A,A7,Calibration!$B:$B,B7)>0,"Yes","No") | W7: By Jim Morris CNN.com Senior Writer BOISE, Idaho (CNN) -- Aided by favorable weather, firefighters said Friday they continued to make gains against wildfires in the northern Rockies. Meantime, Texas, which earlier this week had nearly three dozen large wildfires, now has just 10. "Windy, cool and moist conditions are expected to further help firefighters in Idaho and western Montana make gains on the largest and longest-lasting fires in the country," the Idaho-based National Interagency Fire Center said on its Web site. "We're making slow, but good progress," said a NIFC official. The agency said it expected the recent streak of fire-stopping weather in the northern Rockies could continue over the weekend, although "winds could be a problem." To the south, "cooler temperatures, higher humidity, and precipitation will prevail in Louisiana, Arkansas, Mississippi and eastern Texas," the fire center said. But elsewhere in Texas and in Oklahoma weather is expected to be hot and dry. Nationally, there are 50 wildfires Friday, spread out in 11 states, according to the fire center. The states are: California (1 fire), Idaho (6), Mississippi (1), Montana (23), Nebraska (1), Nevada (1), Oklahoma (3), South Dakota (1), Texas (10), Utah (1) and Wyoming (2). The 10 wildfires reported in Texas on Friday represents a sharp drop from 35 in the state just two days earlier. So far this year, wildfires throughout the United States have burned 6,654,602 acres (10, 397 square miles), the fire center said Friday. By comparison, the land area of New Jersey is 7,418 square miles; Massachusetts is 7,838 square miles; New Hampshire is 8,969 square miles; Vermont is 9,249 square miles; and Maryland is 9,774 square miles. Texas takes lead in number of U.S. wildfires September 6, 2000 More wildfires erupt deep in the hot of Texas September 5, 2000 No Labor Day break for wildfire fighters September 4, 2000 Devils Tower National Monument in Wyoming closed as wildfire burns nearby September 3, 2000 Fires erupt in sizzling Texas as rain dampens West September 2, 2000 Texas State Forest Service Northern Rockies Coordination Center The Army National Guard National Interagency Fire Center Federal Emergency Management Agency • Federal Disaster Aid Ordered for Montana USDA Forest Service National Park Service Note: Pages will open in a new browser window External sites are not endorsed by CNN Interactive. | X7: https://web.archive.org/web/20260620001525/https://www.cnn.com/2000/US/09/08/wildfires.02/index.html | Y7: found | Z7: 385 | AA7: cnn.com | AB7: -6.27 | AC7: -2.5 | AD7: Left-leaning
A8: 5 | B8: 1 | C8: Western/Central/Southeast Drought/Heat Wave (Spring-Fall 2000) | D8: Drought | E8: 20000301 | F8: 20001130 | G8: 9344.8 | H8: 4997.2 | I8: 140 | J8: AK,AL,AZ,CA,CO,FL,GA,HI,IA,ID,IL,IN,KS,KY,MI,MN,MO,MS,MT,NC,ND,NE,NM,NV,OH,OK,OR,SC,SD,TN,TX,UT,VA,WA,WI,WV,WY | K8: 10,11,12,13,14,15,16,17,18,3,4,5,6,7,8,9,National | L8: https://www.baltimoresun.com/2000/03/14/drought-forecast-in-much-of-us-some-states-face-crisis-md-warned-to-expect-less-rain-than-usual/ | M8: Drought forecast in much of U.S.; Some states face crisis; Md ... | N8: Mar 14, 2000 ... These frequently produce heavy rains in the Northwest, drought in the Southeast and more tropical storms and hurricanes in the Atlantic Ocean. | O8: Relevant | P8: -1 | Q8: D | R8: natural_variability | S8: FALSE | T8: The article substantively covers the spring 2000 drought forecast across the exact states in the event metadata, falling within the event window. Forecasters explicitly attribute the deepening drought to La Niña conditions in the eastern tropical Pacific, framing it as a natural climate cycle, with no mention of anthropogenic climate change. | U8: =IF(SUMPRODUCT(--ISNUMBER(SEARCH('National Domains'!$A$2:$A$48,L8)))>0,"Yes","No") | V8: =IF(COUNTIFS(Calibration!$A:$A,A8,Calibration!$B:$B,B8)>0,"Yes","No") | W8: WASHINGTON — Broad swaths of the United States, from Arizona to Georgia and from Nebraska to Ohio, face worsening drought conditions this spring, with potentially costly consequences for agriculture, navigation, water supplies and tourism, federal officials said yesterday. In its first-ever spring drought forecast, the U.S. Commerce Department said federal agencies are mobilizing to provide drought assistance to the affected regions. Officials urged state and local authorities to take steps to prepare for the expected water shortages. “The news is not good,” said Commerce Secretary William M. Daley. “The drought of 1999 remains with us in the new century, and our data indicate drought conditions are probably going to get worse before they get better.” Maryland and Virginia, hit hard by drought last summer, are not included in the federal warning. But both states are expected to get less rain than usual this spring, continuing a pattern of scarce rains that began in July 1998. Maryland has had five months of above-average precipitation in the past 21 months. Long-term drought conditions persist in Garrett County. Other parts of the country face far worse prospects this spring. Two-thirds of the Texas winter wheat crop has been rated in poor condition or worse. Agriculture officials said it was too early to know whether grain prices would be affected by the drought, because well-timed rains could head off serious damage. Louisiana, Mississippi and Alabama recorded their driest February in 106 years of recordkeeping, with no relief in sight. Low water in the upper Great Lakes has forced shipping interests to lighten their freighters by loading less cargo. Wildfires have blackened 208,000 acres this year, nearly four times the acreage burned by this time last year. Federal fire crews are being assigned in expectation of more fires this spring. Some are already battling fires in Kentucky. Agriculture Secretary Dan Glickman said the Clinton administration’s National Drought Policy Commission will issue a report this spring urging stepped-up federal investment in drought preparedness, water conservation and drought-mitigation projects. He said Clinton will ask Congress for an additional $1 billion in the fiscal 2001 budget to make crop insurance more accessible and affordable to farmers. “We must have a drought policy that will provide farmers with the tools to withstand drought, not just survive it,” Glickman said. Droughts are a normal part of climate variation. They cause an average of $6 billion in agricultural losses each year in the United States, twice as much as floods. In some years, droughts cause extraordinary damage. The drought of 1988 — which affected many of the regions facing drought this year — was the most costly weather disaster in U.S. history, with $40 billion in losses. Forecasters blamed this year’s deepening drought on La Nina conditions in the eastern tropical Pacific Ocean, which have persisted since July 1998. Abnormally cold surface water temperatures during La Ninas cause shifts in global weather patterns. These frequently produce heavy rains in the Northwest, drought in the Southeast and more tropical storms and hurricanes in the Atlantic Ocean. Those tropical storms and hurricanes often provide the moisture needed to break droughts. Last year, it took heavy rains from hurricanes Dennis and Floyd, and thunderstorms accompanying a series of cold fronts, to end the drought in Central and Eastern Maryland. The state’s western counties received little relief. Low stream flows The storms provided no relief beyond the East Coast. Stream flows in most of the East are well below normal. Some are at record lows for this time of year, said Charles G. Groat, director of the U.S. Geological Survey. “We should be seeing ground water recharge taking place now, and we’re not seeing that, either,” he said. “Think of it as not having enough money to put in the bank. When the dry summer hits, we may not have enough in savings to get through without problems.” Improved data Weather forecasters did not predict last summer’s drought in the mid-Atlantic states. This year’s forecasts were made possible by improved data gathering and more powerful computers, said D. James Baker, administrator of the National Oceanographic and Atmospheric Administration. “The government can’t guarantee a drenching rain this spring, but we can now provide early warning so people can plan for heat waves and dryness,” Daley said. There will also be seasonal forecasts on flood, drought, hurricanes, heat and storms. There was one bit of good news among the drought warnings. “We see limited risk of flooding this spring,” Daley said. Dry times in Md. Sixteen of the past 21 months have seen below-average precipitation at BWI (months with above-average rainfall in bold). Date Normal Actual (inches) June ’98 3.67 3.23 July ’98 3.69 1.42 Aug. ’98 3.92 0.91 Sept. ’98 3.41 1.27 Oct. ’98 2.98 1.06 Nov. ’98 3.32 1.13 Dec. ’98 3.41 1.27 Jan. ’99 3.05 4.70 Feb. ’99 3.12 2.65 Mar. ’99 3.38 3.46 April ’99 3.09 2.27 May ’99 3.72 1.72 June ’99 3.67 2.04 July ’99 3.69 2.06 Aug. ’99 3.92 6.14 Sept. ’99 3.41 11 .50 Oct. ’99 2.98 2.48 Nov. ’99 3.32 1.95 Dec. ’99 3.41 2.96 Jan. ’00 3.05 3.64 Feb. ’00 3.23 2.01 Mar. ’00 3.38 0.37 Note: March 2000 rainfall through 3/12 SOURCE: National Weather Service | X8: https://web.archive.org/web/20260620001701/https://www.baltimoresun.com/2000/03/14/drought-forecast-in-much-of-us-some-states-face-crisis-md-warned-to-expect-less-rain-than-usual/ | Y8: found | Z8: 869 | AA8: baltimoresun.com | AB8: -3.79 | AC8: 0 | AD8: Left-leaning
A9: 8 | B9: 1 | C9: Tropical Storm Allison (June 2001) | D9: Tropical Cyclone | E9: 20010605 | F9: 20010617 | G9: 15084 | H9: 8522 | I9: 43 | J9: LA,TX | K9: 13,14,15,National | L9: https://www.chron.com/news/houston-texas/article/Tropical-Storm-Allison-takesHouston-Galveston-by-2046653.php | M9: Tropical Storm Allison takesHouston, Galveston by surprise - Chron | N9: Jun 5, 2001 ... The first named storm of the hurricane season, Tropical Storm Allison ... He is a proud native of South Africa, citizen of the United States and ... | O9: Relevant | P9: 0 | Q9: C | S9: FALSE | T9: The article is directly about Tropical Storm Allison making landfall along the Texas/Louisiana coast in June 2001, covering its impacts on Houston, Galveston, and surrounding areas. There is no discussion of climate change, global warming, or any other causal framing — it is purely event reporting on storm impacts and meteorological development. | U9: =IF(SUMPRODUCT(--ISNUMBER(SEARCH('National Domains'!$A$2:$A$48,L9)))>0,"Yes","No") | V9: =IF(COUNTIFS(Calibration!$A:$A,A9,Calibration!$B:$B,B9)>0,"Yes","No") | W9: The first named storm of the hurricane season, Tropical Storm Allison, snuck up on the upper Texas and Louisiana coasts today with a steady rain that flooded streets and bayous. The storm, not even a blip on forecasters' radar screens 12 hours before it was named, remained nearly stationary this evening about 60 miles southwest of Galveston. The storm's leisurely crawl produced sweeping bands of showers that slowly moved up the Gulf Freeway Tuesday night, thoroughly soaking Harris, Brazoria and Galveston counties. Advertisement Article continues below this ad Friendswood and Pearland were hit by the heaviest rain, where 11 inches fell in some places. Flooding is expected in or near Brookside Village in Pearland and areas along and north of Hwy. 6. Travel is not recommended. Roads are impassable and several cars were stranded in Southdown subdivision in Pearland. Clover Field Airport reported 7.9 inches of rain while Friendswood reported 8.35 inches today. Advertisement Article continues below this ad Feeder roads between Hobby Airport and Clear Lake were also reported flooded. A flash flood warning was issued for northern Brazoria County until 10:35 p.m. The slow-moving storm dumped enough rain to close most intersections in the area, including the Gulf Freeway and its access roads at the Bay Area Boulevard. The National Weather Service reported a tornado near Manvel, but further details were not immediately available. Advertisement Article continues below this ad As the rain moved north toward downtown Houston, emergency management officials feared there would be more road closures and flooded bayous. "It's moving so slow that it's really hard to tell, but we're pretty concerned," said Frank Gutierrez, operations manager for the Harris County Office of Emergency Management. Baytown was also in the storm's path. Tides from the three bays that surround the east Harris County city were expected to swell to four or five feet -- two feet above normal -- with winds gusting up to 60 miles per hour. The sustained winds from the storm were not supposed to go over 35 miles-per-hour, however, said Bernard Olive, the city's emergency management director. Advertisement Article continues below this ad The storm's broad arc of showers extended all the way from below Galveston into coastal Alabama. Galveston was the first area to feel the storm's brunt early Tuesday afternoon, when winds gusted over 60 mph and rain slashed across the island for about 90 minutes. Waves crashed over the city's protective seawall, sloshing small portions of seaweed deposits that have plagued the beachfront in recent weeks onto Seawall Boulevard. Many streets in East End neighborhoods were under water but no building flooding was reported. Because of flooding on Highway 87 on the Bolivar Peninsula, the Galveston County Sheriff's Department asked Bolivar Ferry managers to cease service to the peninsula from Galveston. The ferry closed at about 2:30 p.m. and remained shut down less than an hour, when water on Highway 87 began to recede. Advertisement Article continues below this ad Shortly before 3 p.m., Galveston Mayor Roger "Bo" Quiroga recommended a voluntary evacuation of the low-lying 20-mile stretch of island west of the seawall. The recommendation remained in effect for about four hours as water in the area failed to reach dangerous levels. Damage was slight in Galveston. A large temporary signboard fell and damaged a fence at a motel on 61st Street but no injuries were reported. "The Gulf is angry right now," Quiroga said about 4 p.m. "The only thing I don't like is that it happened only four days into the hurricane season." As sunset approached, gusty winds and periodic blowing rain continued in south Galveston County as the last of Allison's storm clouds moved in from the gulf. Advertisement Article continues below this ad Kemah Waterfront also faced waves crashing against its bulkheads, and restaurants along the Clear Creek Channel were closed. "The problem is not from the rain but from waves on the bay side crashing over the bulkhead," said Kemah Police Chief Tommie Buchanan. The restaurants, which were hit hard by Tropical Storm Frances in 1998, were not flooded Tuesday. When most Houstonians awoke Tuesday, Allison was officially an upper level low pressure system centered 150 miles offshore in the northwestern Gulf of Mexico, and wasn't given much chance of strengthening. But by 2 p.m. an air force reserve "Hurricane Hunter" aircraft had flown into the weather system and discovered a full-blown tropical storm. Advertisement Article continues below this ad "It went right from nothing to a tropical storm," said Charles Roeseler, a forecaster at the National Weather Service's Alvin office. "We had convection persisting out in the Gulf yesterday (Monday), but last night was the first sign of any organization." Roeseler said forecasters initially thought they were dealing with a "hybrid" weather system, a cross between a tropical system and an extra-tropical system. They believed two essential ingredients for concocting a tropical system -- light high-altitude winds and a warm sea surface -- were missing from the stew. But when the aircraft flew through the system, the core temperatures were warmer than expected, and the winds increased significantly during the day. The storm developed so rapidly, Roeseler said, there was hardly any time to react. Advertisement Article continues below this ad "I don't think we are going to have time to worry," the forecaster said Tuesday afternoon as Allison began pushing ashore. Chronicle reporters Kevin Moran, Cindy Horswell and Ruth Rendon contributed to this story. | X9: https://web.archive.org/web/20260620001907/https://www.chron.com/news/houston-texas/article/tropical-storm-allison-takeshouston-galveston-by-2046653.php | Y9: found | Z9: 904 | AA9: chron.com | AB9: -0.75 | AC9: 0 | AD9: Left-leaning
A10: 8 | B10: 2 | C10: Tropical Storm Allison (June 2001) | D10: Tropical Cyclone | E10: 20010605 | F10: 20010617 | G10: 15084 | H10: 8522 | I10: 43 | J10: LA,TX | K10: 13,14,15,National | L10: https://www.chron.com/life/article/Fresh-news-Tropical-Storm-Allison-dumps-on-city-2048790.php | M10: Fresh news: Tropical Storm Allison dumps on city - Chron | N10: Jun 14, 2001 ... Tropical Storm Allison broke Houston's heart, but not its spirit. ... None of the hurricanes hit the United States. ... June 14, 2001. Chron ... | O10: Relevant | P10: 0 | Q10: C | S10: FALSE | T10: The article is clearly about Tropical Storm Allison's impact on Houston, TX in June 2001, covering damages, flooding, and recovery efforts. There is no mention of climate change or any causal attribution beyond describing the storm's unusual behavior (quick formation, circling back) in purely meteorological terms. | U10: =IF(SUMPRODUCT(--ISNUMBER(SEARCH('National Domains'!$A$2:$A$48,L10)))>0,"Yes","No") | V10: =IF(COUNTIFS(Calibration!$A:$A,A10,Calibration!$B:$B,B10)>0,"Yes","No") | W10: Tropical Storm Allison broke Houston's heart, but not its spirit. It dumped roughly 3 feet of rain on the city, caused $1 billion in damage and at least 20 deaths. It was the worst flooding in Houston since 1994, when 17 people were killed, 22,000 were left homeless and $700 million worth of property was damaged. Why was this storm so bad? Advertisement Article continues below this ad Weather forecasters called the storm unusual because it formed quickly in the Gulf of Mexico, dumped a load of rain on the area and then circled back a few days later, unloading more rain on the already soaked ground. What areas were hardest hit? Allison skipped around the city. Generally, parts of downtown Houston, the Texas Medical Center and homes located near Houston's many bayous and low-lying areas suffered the most damage. Such areas as Katy, west Houston, Baytown and Galveston were largely spared the brunt of the damage. Advertisement Article continues below this ad What is the extent of damage to area schools? More than half of the Houston Independent School District's 300 schools reported flood damage and more than a dozen were still dealing with substantial water damage earlier this week. The worst damage was reported at Edison and Holland middle schools, and Pleasantville, R.P. Harris, Scarborough, J.R. Harris, Browning, Concord, Allen, Mitchell, Petersen, Kashmere Gardens and Plum Creek elementary schools. Some North Forest ISD schools were so badly flooded that summer school classes have been postponed until Monday. Advertisement Article continues below this ad Six Aldine ISD schools, including Aldine High School, Hall Education Center, Smith Academy and Conley, Mendel and Johnson elementary schools, were damaged by the flood. The University of Houston reported most of the 105 buildings on its main campus suffered flood damage. Institutions at the Texas Medical Center lost as many as 30,000 research animals. Where did all the waist-high water go? It has either receded back into the bayous or has been absorbed into drainage systems. In some cases, the city had to use pumps to force the water through the drainage system because it's not set up to handle the quantity received in a short period of time. Advertisement Article continues below this ad Does this mean we are going to have a severe hurricane season? Not necessarily. Government forecasters are predicting a "normal" hurricane season -- eight to 11 storms, five to seven of them hurricanes -- or a calmer season that the past three seasons. Last year there were 14 tropical storms, including eight hurricanes and three major hurricanes. None of the hurricanes hit the United States. What's the difference between a tropical storm and a hurricane? Advertisement Article continues below this ad Tropical storms form and receive names when their circulating winds reach 39 miles per hour. They become hurricanes when their winds reach 74 mph and major hurricanes when their winds reach 111 mph. What kind of help is needed? Volunteer Houston has heard from 100 agencies that need assistance. Agencies need help in moving families out of their flooded homes, collecting donated items and making general repairs to damaged shelters. Advertisement Article continues below this ad Call Volunteer Houston at 713-965-0031 to learn about what you can do to help. | X10: https://web.archive.org/web/20260620002006/https://www.chron.com/life/article/fresh-news-tropical-storm-allison-dumps-on-city-2048790.php | Y10: found | Z10: 542 | AA10: chron.com | AB10: -0.75 | AC10: 0 | AD10: Left-leaning
A11: 8 | B11: 3 | C11: Tropical Storm Allison (June 2001) | D11: Tropical Cyclone | E11: 20010605 | F11: 20010617 | G11: 15084 | H11: 8522 | I11: 43 | J11: LA,TX | K11: 13,14,15,National | L11: https://www.nytimes.com/2001/06/11/us/tropical-storm-leaves-16-dead-in-2-gulf-states.html | M11: Tropical Storm Leaves 16 Dead In 2 Gulf States - The New York Times | N11: Jun 11, 2001 ... ... Tropical Storm Allison, which left 15 people dead and about 10000 ... https://www.nytimes.com/2001/06/11/us/tropical-storm-leaves-16 ... | O11: Relevant | P11: 0 | Q11: C | S11: FALSE | T11: The article directly covers Tropical Storm Allison's impacts on Texas and Louisiana during the event window (June 2001), including deaths, flooding, and damage. There is no mention of climate change, global warming, or any causal attribution — it is pure event reporting. | U11: =IF(SUMPRODUCT(--ISNUMBER(SEARCH('National Domains'!$A$2:$A$48,L11)))>0,"Yes","No") | V11: =IF(COUNTIFS(Calibration!$A:$A,A11,Calibration!$B:$B,B11)>0,"Yes","No") | W11: Advertisement Supported by Tropical Storm Leaves 16 Dead In 2 Gulf States By Ross E. Milloy As storm-weary residents emerged from their waterlogged homes here today, they faced highways littered with jackknifed 18-wheeled trucks, roads lined with abandoned cars, trash and tires and whole neighborhoods underwater. Tropical Storm Allison, which caught just about everyone off guard when it struck with renewed strength on Friday and early Saturday, hammered southeast Texas for nearly a week, leaving at least 15 people dead and about 10,000 homes and 5,000 buildings damaged. One person also died in Louisiana as a result of the storm. [Page A12.] With the threat of rain easing today in Texas, Gov. Rick Perry toured the area by helicopter with Mayor Lee P. Brown and officials from the Federal Emergency Management Administration. Mayor Brown has estimated that at least 5,000 buildings in Houston were damaged by water, with losses perhaps reaching $1 billion. In light of the storm's devastation, President Bush has declared Harris County and 27 other southeast Texas counties a federal disaster area, eligible for loans to local governments and individuals. ''We're still assessing just how much damage we've got, and it may be some time before we've got an accurate count,'' said Paul Bettencourt, the Harris County tax assessor who estimated that 10,000 homes had been damaged. ''Many areas are still flooded and we haven't been able to get into them yet.'' At the world's largest medical facility, the Texas Medical Center near downtown -- a complex of more than a dozen hospitals and research laboratories -- dozens of volunteers worked furiously today to unload crates of dry ice to cool laboratory specimens put at risk by power failures over the weekend. Claire Bassett, a vice president at the Baylor College of Medicine, said thousands of laboratory animals, mainly rats and mice, had been killed when storm waters flooded their facilities overnight Friday. ''We won't know just how bad the loss is until we can get in there, but we're estimating the losses of lab animals throughout the Texas Medical Center at several thousand,'' Ms. Bassett said. But worse, she said, was the loss of scientific research and specimens flooded or destroyed when the power failed. One of those most affected by the loss was Dr. Bonnie Dunbar, a professor of molecular and cellular biology at the college, who said she lost more than 20 years worth of laboratory specimens and clones. ''It's all gone, more than 20 years of work, and there are hundreds of other like me,'' Dr. Dunbar said. ''We've lost meticulous research, doctoral theses, experiment records, biological samples, all gone.'' Dr. Dunbar, who was to have left for Kenya on Monday as part of a Fulbright scholarship program to perform pediatric H.I.V. research in Africa, has also been displaced from her home: the rains knocked out power and telephones in her 40-story apartment building, and she has been forced to move. In the hard-hit northeastern part of the city, more than 3,300 people took refuge on Saturday night in the Lakewood Church, which eventually became the largest refugee center of more than 30 across the city. ''People just started coming and kept on coming because they had no place else to go,'' the church's pastor, the Rev. Joel Osteen, said. ''Eventually, city workers started dropping people off here in dump trucks because they were the only vehicles that could get through the water.'' Short of food by Saturday morning, Mr. Osteen recruited two brothers- in-law with Chevy Suburbans and a family friend for a visit to Sam's Discount Club, where they spent $3,000 on ingredients for sandwiches. ''Every time we returned with a load of food, the crowd of people would have gotten larger and we'd have to go make another trip,'' he said. But by today, the local news media had reported about food shortages at the church, and area residents bearing food, diapers, clothing and bottled water created a traffic jam in the streets outside the church. Signs of the flooding were apparent in the neighborhoods of the Lakewood area, with soaked carpets, furniture and clothing strewn in dozens of muddy yards. In addition to the staggering job of cleaning up after the flood, there was also the burden of mourning, as details of the deaths the city sustained over the weekend emerged. One couple, walking along the banks of White Oak Bayou, were swept away by a rapidly rising torrent, their bodies later found in the branches of nearby trees. A man trying to save a television set was electrocuted when he reached for its antenna; his mother also was electrocuted as she tried to help him. At least five drivers died after being caught by high water in their vehicles. But one of the most shocking accounts was the death of Kristie Lee Tautenhahn, 42, a clerk at a downtown law firm. Warned that vehicles in the Bank of America building's underground garage should be moved to higher ground, she took an elevator down to get her car from the fourth level of the garage early Saturday morning. At the third level, water flooded into the elevator, shutting off power, and Ms. Tautenhahn drowned there, alone. ''To die in an elevator is just tragic,'' John Tautenhahn, her cousin, told The Houston Chronicle. ''This is just devastating.'' Much of downtown remained crippled today, without power or working telephones. Parts of the dozen miles of tunnels beneath the city, built to help downtown office workers escape the summer heat and filled with food courts and stores, were flooded. At the Harris County Jail, which is adjacent to Buffalo Bayou, 3,000 inmates had to be moved to other facilities when the floods knocked out electricity and water. Continental Airlines, based in Houston, resumed flights today after canceling more than 1,000 flights on Saturday. And all across the city, as the sun finally poked through still-cloudy skies, residents shared stories of what they are calling the ''Great Flood of 2001.'' Jennifer Brazzel, an artist and interior designer, was stranded when she tried to drive her Toyota 4-Runner five miles to a friend's house on Friday night. Her car flooded just off Rice University's campus and a block from the Rice Village Shopping Center. ''I was trying to drive to my friend's house and all of a sudden Rice Boulevard was like a river,'' Ms. Brazzel said. ''Water was over my dash.'' Ms. Brazzel managed to get the car door open, and fought her way to higher ground, although the current knocked her down several times along the way. The sun had risen before she got home. Linda Gomez's husband was moving cars to higher ground when Ms. Gomez heard a noise in the backyard and saw water bursting from a manhole cover. When she went to investigate in the dark, she slipped into the hole. The water was only a foot deep but the lid was stuck and the current was strong. She was treated for bruises and scrapes at a hospital on Friday. ''When I got home the water was starting to rise,'' she said. She disconnected electrical appliances and began to move furniture higher, but by 10:30 that night the water had started coming into the house. ''By then it was too late,'' Ms. Gomez said. ''The water came into the house so fast. We were trying to get things up. There was no way to get out.'' As the water continued to rise in the one-story house, to an eventual height of almost five feet, they moved to the attic. ''Neighbors were screaming on both sides,'' Ms. Gomez said. ''The homeless men who sleep in the park across the street were screaming for help. I told my husband we have to figure out a way to make a hole in the roof.'' She eventually reached her son, who works with the Sheriff's Department, by cell phone. ''I told him I don't think we'll make it out of here,'' Ms. Gomez said. About 8 a.m. Saturday, a Houston Fire Department boat evacuated Ms. Gomez and her family. Today, they returned to find their home filled with mud and debris. As she surveyed the damage, Ms. Gomez said: ''I was raised in this house. I'm 54 years old. And I've never seen anything like this.'' Advertisement | X11: http://web.archive.org/web/20210301174525/https://www.nytimes.com/2001/06/11/us/tropical-storm-leaves-16-dead-in-2-gulf-states.html | Y11: found | Z11: 1384 | AA11: nytimes.com | AB11: -8.02 | AC11: -2.5 | AD11: Left-leaning
A12: 9 | B12: 1 | C12: Severe Storms and Tornadoes (April 2002) | D12: Severe Storm | E12: 20020427 | F12: 20020428 | G12: 3663.9 | H12: 2093.8 | I12: 7 | J12: NATIONAL | K12: National | L12: http://www.cnn.com/2002/WEATHER/04/28/storm.deaths/index.html | M12: Twisters leave at least 6 dead - April 29, 2002 - CNN | N12: Apr 29, 2002 ... The twister system in the Midwest killed three people in three states early Sunday, while three others died in Maryland when a tornado ... | O12: Relevant | P12: 0 | Q12: C | S12: FALSE | T12: The article directly covers the April 28, 2002 tornado outbreak across Missouri, Illinois, Kentucky, and Maryland, matching the event window and geography. There is no discussion of climate change or any causal attribution beyond meteorological reporting of impacts and damages. | U12: =IF(SUMPRODUCT(--ISNUMBER(SEARCH('National Domains'!$A$2:$A$48,L12)))>0,"Yes","No") | V12: =IF(COUNTIFS(Calibration!$A:$A,A12,Calibration!$B:$B,B12)>0,"Yes","No") | W12: PADUCAH, Kentucky (CNN) -- Tornadoes swept through southeastern Missouri, Illinois, western Kentucky and Maryland on Sunday, killing at least six people and damaging dozens of buildings, authorities said. The twister system in the Midwest killed three people in three states early Sunday, while three others died in Maryland when a tornado touched down there Sunday night. The pattern of damage in the Midwest led authorities to suspect that a single tornado -- not several -- caused most of the destruction early Sunday, said Jim Packett, a meteorologist with the National Weather Service in Paducah. Packett said that authorities will not definitively know which twister or twisters caused the damage for several days. "We may end up with a tornado path length of over 100 miles, if it all pans out like we think," said Packett, noting there was damage in at least 10 Midwest counties. An F3 tornado -- about 4 miles long and packing winds up to 180 miles an hour, average strength for such a storm -- touched down around 12:40 a.m. (1:40 a.m. EDT) about 5 miles southwest of Marble Hill, Missouri, Packett said. The twister killed a 12-year-old boy in Marble Hill, about 90 miles south of St. Louis, and injured 16 others, a sheriff's dispatcher said. In Dongola, Illinois, about 30 miles south of Carbondale, the tornado killed an elderly woman outside her mobile home, a sheriff's dispatcher said. Six others were injured and "a number" of homes and businesses were damaged, said Packett. The storm caused damage in Illinois' Pope and Johnson counties as it made its way east and to the state's southern tip, said Packett. It then crossed the Ohio River into western Kentucky, causing damage in Livingston, Crittenden and Hopkins counties. The twister blew 46 full freight cars off the railroad tracks in Providence before hitting Caldwell County, around Princeton, where 29 people were taken to the hospital and a number of homes and mobile homes were destroyed, according to Packett. Officials in Breckinridge County, Kentucky, said a man was killed outside his mobile home on the southwest side of Irvington, about 40 miles southwest of Louisville. The storm also damaged a subdivision on the south side of town. "There was a pretty good-size motor home turned upside down on a boat," said Breckinridge Sheriff's Deputy Sandra Wood. The tornado Sunday night in southern Maryland killed three people and injured dozens of others. The twister slammed into businesses and houses, forcing people into shelters, according to government and weather officials. The tornado went through a 12-mile area, said Nina Voehl of the Charles County Sheriff's Office, starting in the small town of La Plata and going east through what is largely a rural area with a lot of farmland. After passing through the town of Benedict, the system plowed across the Patuxent River and entered Calvert County. The weather system produced golf-ball sized hail all along the way. Two people were killed in La Plata in Charles County, about 25 miles south of Washington, Charles County officials said. One was in a residence and the other was in a vehicle at the corner of Routes 301 and 6. Another was killed in Hallowing Point near Prince Frederick in next-door Calvert County, said Don Hall, the county's emergency management director. Charles County Commissioner Murray Levy said he saw the tornado touch down not far from his home, just outside La Plata. "I'd never heard anything like that in my life," he said. "My wife and I were on the back porch and she said, 'Do you hear that?' And it was a roar, and then I saw the funnel, and then it touched down just to the east of our house." About 12 people from Charles County were taken to trauma centers in the region and at least 81 people from the county were sent to area hospitals for treatment, Voehl said. At least 35 people were staying at a shelter set up at local high school in Charles County and 11 families in Calvert County have been put up by the Red Cross in hotels, Maryland officials said. Strong winds and hefty hail battered Bedford County, Virginia, on Sunday afternoon, damaging at least 50 homes but causing no major injuries, officials said. The system knocked down a number of buildings in Bedford, a city of 70,000 about 20 miles east of Roanoke, said county Sheriff Mike Brown. Authorities shut down the downtown area and a number of streets "just in case anybody had looting on their mind," Brown said. National Weather Service meteorologist Jim Hudgins said the storm, which moved through the area around 4:30 p.m., could have been a tornado or just strong winds. The Virginia storms did belong to a different band of storms than the one that caused a tornado in Maryland, he said. Most of the damage happened along Route 460, a major four-lane highway linking Roanoke and Lynchburg that runs through the center of town, Brown said. The Red Cross was on the scene and the local Wal-Mart was serving food, he said. | X12: https://web.archive.org/web/20260620002226/https://www.cnn.com/2002/WEATHER/04/28/storm.deaths/index.html | Y12: found | Z12: 847 | AA12: cnn.com | AB12: -6.27 | AC12: -2.5 | AD12: Left-leaning
A13: 9 | B13: 2 | C13: Severe Storms and Tornadoes (April 2002) | D13: Severe Storm | E13: 20020427 | F13: 20020428 | G13: 3663.9 | H13: 2093.8 | I13: 7 | J13: NATIONAL | K13: National | L13: http://www.cnn.com/2002/WEATHER/04/29/storm.deaths/index.html | M13: Killer tornado becomes one for the books in Maryland - April 29, 2002 | N13: Violent storms kill at least 6 in 4 states. April 29, 2002 Posted: 11:07 PM EDT (0307 GMT) ... "One of the strongest tornadoes ever to strike the state of ... | O13: Relevant | P13: 0 | Q13: C | S13: FALSE | T13: The article directly covers the April 27-28, 2002 severe storm/tornado outbreak, specifically the F5 tornado in La Plata, Maryland, including deaths, injuries, and destruction — matching the event window and geography. There is no mention of climate change, global warming, or any causal attribution beyond describing the storm's immediate meteorological context. | U13: =IF(SUMPRODUCT(--ISNUMBER(SEARCH('National Domains'!$A$2:$A$48,L13)))>0,"Yes","No") | V13: =IF(COUNTIFS(Calibration!$A:$A,A13,Calibration!$B:$B,B13)>0,"Yes","No") | W13: LA PLATA, Maryland (CNN) -- A tornado in southern Maryland that killed three people and left a "war zone" of destruction in its wake was one of the strongest to ever hit the state, a National Weather Service spokeswoman said Monday. A statement from the National Oceanic and Atmospheric Administration said its damage assessment team rated the tornado an F5 on the Fujita Tornado Damage Scale, "a monster of a tornado" with winds in the 261-318 mph range. The storm was one of a series of storms that claimed at least six lives Sunday, officials said. The path of the tornado began more than 10 miles west of La Plata, then strengthened to F5 as it reached the town, where two of the three victims died and there was widespread devastation. "The magnitude of the damage is very impressive," Watson said. "One of the strongest tornadoes ever to strike the state of Maryland ... not just a few buildings demolished but many buildings demolished." Monday, search crews rushed from house to house in La Plata looking for anyone trapped in debris. Dozens of people were injured in the storm. One of the victims, who lived just outside La Plata, was 51-year-old William Gardner Erickson, who died when his house collapsed. Another La Plata resident was found dead in a vehicle near the main thoroughfare in this town of 6,500. A report that a third Charles County resident had died Monday proved false. The third fatality was near Prince Frederick, further east in neighboring Calvert County. "It's devastating," said Nina Voehl of the Charles County Sheriff's Department. "There are many businesses here that are flattened, and there are no roofs [on many buildings.] The Red Cross has no office -- the roof was totally taken off." The Maryland tornado was just one example of Mother Nature's fury Sunday, a day marked by several strong storms. Early Sunday, a series of tornadoes swept through southeastern Missouri, Illinois and western Kentucky, killing three people, and damaging homes and buildings. The tornado that hit Maryland was part of a storm system with heavy rain, high winds and hail that rumbled east from the Ohio Valley. Strong wind and hail the size of Ping Pong balls battered Bedford County, Virginia, Sunday afternoon, damaging at least 50 homes east of Roanoke, officials said. There were no reports of injuries, but stores in downtown Bedford had extensive damage. In La Plata, Mayor William Eckman said, "It's like a war zone out there." The hardest-hit areas of La Plata were evacuated, and schools and government offices were closed, Voehl said. Dozens of area families left homeless were being sheltered by the Red Cross. The tornado also knocked over the town's 125-foot water tower, and citizens were asked to conserve water, Eckman said. Structural engineers were assessing the integrity of buildings and planned to fly over the community Monday. About 4,800 households in the area, including nearby Benedict and Hughesville, remained without electrical power, Voehl said. At the height of the storm, there were 24,710 homes without electricity. La Plata's hospital, Civista Medical Center, had damage to windows and its parking lot. "The alert was sounded in time to have all of our staff and patients move away from the windows," said spokeswoman Chris Stefanides. "We're continuing our operations here, but we are still in an emergency situation and accepting victims from around the community." Charles County Commissioner Murray Levy said he saw the tornado touch near his home, just outside La Plata. "I'd never heard anything like that in my life," he said. "My wife and I were on the back porch and she said, 'Do you hear that?' And it was a roar and then I saw the funnel, and then it touched down just to the east of our house." About 12 people from Charles County were taken to trauma centers in the region and about 80 people were sent to area hospitals for treatment, Voehl said. At least four people were taken to Washington Hospital Center in Washington, where two were reported in critical condition. -- CNN Assignment Editor Patrick Davis contributed to this report. | X13: https://web.archive.org/web/20260620002414/https://www.cnn.com/2002/WEATHER/04/29/storm.deaths/index.html | Y13: found | Z13: 690 | AA13: cnn.com | AB13: -6.27 | AC13: -2.5 | AD13: Left-leaning
A14: 9 | B14: 3 | C14: Severe Storms and Tornadoes (April 2002) | D14: Severe Storm | E14: 20020427 | F14: 20020428 | G14: 3663.9 | H14: 2093.8 | I14: 7 | J14: NATIONAL | K14: National | L14: https://www.nytimes.com/2002/05/07/science/finding-the-what-when-where-and-why-of-the-supertwister.html?eafs_enabled=false | M14: Finding the What, When, Where and Why of the Supertwister | N14: May 7, 2002 ... Fujita described as merely ''devastating,'' account for 1 percent or so of the 1,000 tornadoes that form in the United States each year. | O14: Relevant | P14: 0 | Q14: C | S14: FALSE | T14: The article substantively covers the April 28, 2002 F-5 tornado that struck La Plata, Maryland, discussing its damage, casualties, and the science of tornado formation. There is no mention of climate change or any causal attribution beyond natural meteorological dynamics. | U14: =IF(SUMPRODUCT(--ISNUMBER(SEARCH('National Domains'!$A$2:$A$48,L14)))>0,"Yes","No") | V14: =IF(COUNTIFS(Calibration!$A:$A,A14,Calibration!$B:$B,B14)>0,"Yes","No") | W14: LA PLATA, Md., May 2 -- At dusk on April 28, this town 30 miles south of Washington became No. 94 on the list of unlucky places struck since 1880 by F-5 tornados, the rare class of supertwisters that produces almost unimaginable destruction. Four people died, more than 100 were injured, and a raw gash was cut across 24 miles of forests, lawns, roads and farmland. Four days later, a team assembled by the National Weather Service to review the damage and assess forecasting skill walked house to house, trying to gauge the tornado's destructive power more thoroughly. The team was also eager to glean new clues about the most potent class of tornado, which despite decades of storm chasing and improved radar and satellite monitoring remains a deadly enigma. Although meteorologists have greatly improved their understanding of how certain conditions generate especially powerful thunderstorms and how these towering heat engines can spin out twisters, the experts have yet to figure out what ingredients spawn an F-5. ''This is still fundamentally one of the things we can't predict,'' said Dr. Harold E. Brooks, a research meteorologist at the National Severe Storms Laboratory in Norman, Okla. ''I'm not even sure we know what measurements we need to take to try to understand them.'' [A potent tornado killed two people on Sunday in Happy, Tex. Meteorologists had not yet finished analyzing its strength by Monday evening.] Some twisters explode from unremarkable thunderheads, and then there are towering supercells, thunderstorms that are tornado makers, that pass without incident, said Thomas P. Grazulis, a meteorologist and the author of ''The Tornado: Nature's Ultimate Windstorm,'' published last year. ''Progress is incredibly slow, because you have three or four case studies a year,'' he said. ''But they all turn out to be different.'' The meteorologists and engineers who gathered here were looking for physical manifestations of the storm's intensity, assessing the sturdiness of shattered houses and the distance traveled by heavy objects. It is no simple task, because every building is built differently and responds to wind differently. Also, damage is just partly a function of wind. More often, it results from objects carried in the air. ''Pure wind doesn't do the damage,'' said Timothy P. Marshall, a structural engineer and meteorologist at an engineering firm in Houston and a volunteers in federal studies of tornado damage. ''The churning debris acts like a blender.'' Another complication is storm speed. Slow-moving tornadoes can be particularly devastating: they grind away, sometimes for minutes at a time. One F-5 in Texas stayed on top of a house for three minutes, Mr. Marshall said, adding: ''They never had a chance. Trees were completely shredded. The road pavement was gone. The ground was gone.'' The destruction of a building, too, is not just a result of a storm, but also of the quality of construction. In and around La Plata, many houses -- old and new -- did not appear well built, Mr. Marshall said, with frames weakly connected to foundations. The official determination of the intensity will not be released for many weeks. The F scale for tornadoes mainly considers damage, not wind speed. It was devised in 1971 by Dr. T. Theodore Fujita, a Japanese-born meteorologist and damage expert whose first experience investigating a disaster zone was at Hiroshima. In going from wimpy, almost inconsequential F-0 to devastating F-5, Dr. Fujita, who died in 1998 after a long career at the University of Chicago, nearly ran out of descriptive terms. The most potent storms produce ''incredible phenomena,'' Dr. Fujita wrote. Among those, he said, ''automobile-size missiles fly through the air in excess of 100 meters'' and sturdy houses are ''lifted off foundations and swept away.'' In this town of 6,500 people and the other blasted parts of Charles County along the tornado's 24-mile path, incredible phenomena occurred. La Plata's water tower crumpled like a stomped daddy longlegs. The tornado destroyed 344 houses and businesses. But just steps outside its quarter-mile-wide path, unscathed tulips nodded in the breeze. The randomness and unpredictability of what survives and what is pulverized after such tornadoes is an echo of the persistent unpredictability of the most powerful storms themselves, experts say. Generally, conditions are prime when cool dry air flows over warm, moist air near the surface, setting up turbulent conditions in which air masses clash. In the biggest storms, or supercells, the air rotates as updrafts burst toward the stratosphere. These effects can create whirling vortexes deep inside a storm that, if jogged just right, push down toward the ground, as well as up into the sky. Finding the right trigger at the right time is the trick that keeps the giant storms rare. Together, F-5's and F-4's, which create damage that Dr. Fujita described as merely ''devastating,'' account for 1 percent or so of the 1,000 tornadoes that form in the United States each year. Just 10 percent are F-2 or higher. In what many experts say is the definitive analysis of accounts of past tornadoes, Mr. Grazulis, who runs the Tornado Project, a business centered on tornado lore in St. Johnsbury, Vt., cites a storm that exploded through Christian, Ill., on April 24, 1880, as the first American F-5. The destruction is mainly focused in the Midwest and South, across a zone called Tornado Alley where cool dry Canadian air often clashes with warm, moist air from the Gulf of Mexico. But the destruction extends as far north as Saskatchewan and -- now -- as far east as Maryland. For Tom Posey Sr., 72, a lifelong resident, the meaning of F-5, his personal ''incredible phenomenon,'' was the utter disintegration of Posey's, a grocery store that his kin ran in a 40-year-old building that he owned. He kicked at the rubble and supervised two young men as they removed a safe. The roof was long gone, and the walls only vaguely represented by flung, shattered cinder blocks. Incredibly, some sets of shelves still stood, still holding bottles of salad dressing and jars of spaghetti sauce. The sign out front, which had adjustable plastic letters that before the storm had advertised a special on a Maryland delicacy, stuffed ham, was ragged, but still stood. Mr. Posey pointed out that someone had rearranged the letters that had not blown away. One side of the sign now displayed, ''We Are Tuff.'' | Y14: found | Z14: 1056 | AA14: nytimes.com | AB14: -8.02 | AC14: -2.5 | AD14: Left-leaning
A15: 11 | B15: 1 | C15: Tropical Storm Isidore (September 2002) | D15: Tropical Cyclone | E15: 20020925 | F15: 20020927 | G15: 2001 | H15: 1150 | I15: 5 | J15: AL,LA,MS | K15: 13,14,15,6,7,8,National | L15: http://www.cnn.com/2002/WEATHER/09/30/lili/index.html | M15: Hurricane Lili batters Caymans - Sep. 30, 2002 - CNN | N15: Sep 30, 2002 ... Near Kiln, Mississippi, locals are still burning debris and drying carpets after Tropical Storm Isidore. They are keeping a close eye on ... | O15: Trash | S15: FALSE | T15: This article is primarily about Hurricane Lili battering the Cayman Islands (September 30, 2002), not Tropical Storm Isidore. While Isidore is briefly mentioned as a geographic reference point for Lili's potential landfall, the article does not substantively cover Isidore's impacts, damages, costs, or recovery in the affected states (AL, LA, MS). | U15: =IF(SUMPRODUCT(--ISNUMBER(SEARCH('National Domains'!$A$2:$A$48,L15)))>0,"Yes","No") | V15: =IF(COUNTIFS(Calibration!$A:$A,A15,Calibration!$B:$B,B15)>0,"Yes","No") | W15: Hurricane Lili batters Caymans Islands reel under wind, rain MIAMI, Florida (CNN) -- Hurricane Lili lashed the Caribbean islands of Little Cayman and Cayman Brac Monday, and a top forecaster worried it might erupt into a major force in the Gulf of Mexico before hitting U.S. shores. The fourth hurricane of the 2002 hurricane season could threaten the Louisiana or upper Texas coast by early Thursday, said Max Mayfield, director of the National Hurricane Center in Miami. Landfall is likely to be between Galveston, Texas, and Mobile, Alabama -- possibly around Lake Charles, Louisiana, said CNN meteorologist Chad Myers. That would put it near where Tropical Storm Isidore made landfall a week ago. Mayfield said it is too early to tell where Lili might come ashore in the United States. Lili was upgraded Monday from a tropical storm to a Category 1 hurricane and its maximum sustained winds have strengthened to 80 mph. At 11 p.m. ET, Lili was about 110 miles southeast of Cuba's Isle of Youth, moving west-northwest at 10 mph, and was producing heavy rain across Jamaica, the Cayman Islands and eastern Cuba, according to the National Hurricane Center. "These rains could cause life-threatening flash flooding and mudslides," a hurricane center advisory said. The Associated Press reports that flooding and mudslides killed four people Sunday in Jamaica. Four others were killed last Tuesday on the island of St. Vincent. A ham radio operator on Cayman Brac told the NHC that the storm had downed trees and powerlines and damaged the roofs of several homes on the tiny island. Mayfield said Lili should reach western Cuba early Tuesday before heading north to the Gulf of Mexico. He said the first concern in the Gulf would be for the safety of people working on oil-drilling platforms. Potentially more dangerous Lili is potentially more dangerous than Isidore, he said. "Isidore actually was a very powerful Category 3 hurricane, but then it moved over the Yucatan Channel and the Yucatan Peninsula and it actually sat over land for several days," Mayfield told CNN. "That really allowed it to weaken, and it never did become back to a hurricane once it moved back out of the Gulf of Mexico." But Lili, he said, "is going to just skirt the western tip of Cuba. It's not mountainous there. It's relatively flat. It's not very wide -- so I don't really see any real impact there. That's why we're very concerned that it could go ahead and strengthen over the warm waters of the Gulf of Mexico." Earlier, forecasters at the National Hurricane Center anticipated Lili could be a Category 2 hurricane (winds of 96-110 mph) in the north-central Gulf by late Thursday or Friday. A hurricane warning remained in effect for the Cayman Islands and the Cuban provinces of Matanzas, Ciudad de la Habana, La Habana, Pinar del Rio and the Isle of Youth. A tropical storm warning covered the rest of Cuba. Jamaica and the southwestern peninsula of Haiti were deluged over the weekend with heavy rain, as they were just a week ago when Hurricane Isidore rammed through just to the south of Lili's current track. Kyle weakens off Bermuda Meanwhile, the remnants of Tropical Storm Kyle have reformed as a tropical depression about 350 miles south-southwest of Bermuda -- about 220 miles south of its previous position. The storm's maximum sustained winds have dropped to 35 mph and it is nearly stationary. Forecasters do not expect any significant change in strength or movement. A tropical storm watch remains in effect for Bermuda. | X15: https://web.archive.org/web/20260620002652/https://www.cnn.com/2002/WEATHER/09/30/lili/index.html | Y15: found | Z15: 592 | AA15: cnn.com | AB15: -6.27 | AC15: -2.5 | AD15: Left-leaning
A16: 11 | B16: 2 | C16: Tropical Storm Isidore (September 2002) | D16: Tropical Cyclone | E16: 20020925 | F16: 20020927 | G16: 2001 | H16: 1150 | I16: 5 | J16: AL,LA,MS | K16: 13,14,15,6,7,8,National | L16: http://www.cnn.com/2002/WEATHER/10/05/lili/ | M16: Lili damage estimated at $600 million - Oct. 5, 2002 - CNN | N16: Oct 5, 2002 ... But Lili, the first hurricane to hit U.S. shores in 2002, could have been far worse. ... Tropical Storm Isidore, which came ashore in almost the ... | O16: Borderline | S16: FALSE | T16: The article is primarily about Hurricane Lili (October 2002), not Tropical Storm Isidore (September 2002). It mentions Isidore only in passing in a single sentence noting its $100 million in insured losses, which is insufficient to constitute substantive coverage of the Isidore event. | U16: =IF(SUMPRODUCT(--ISNUMBER(SEARCH('National Domains'!$A$2:$A$48,L16)))>0,"Yes","No") | V16: =IF(COUNTIFS(Calibration!$A:$A,A16,Calibration!$B:$B,B16)>0,"Yes","No") | W16: Lili damage estimated at $600 million NEW YORK (CNN) -- Hurricane Lili could cost U.S. insurers $600 million in claims, the Insurance Information Institute said Saturday. Lili rushed ashore Thursday morning, sweeping through central Louisiana and spreading heavy rain and winds through Mississippi, Arkansas, Tennessee and parts of Texas. But Lili, the first hurricane to hit U.S. shores in 2002, could have been far worse. Just a few hours before landfall, the storm carried winds of 145 mph, but those dropped to 100 mph before the storm came ashore. The institute's preliminary information came from a survey of insurers and an average of initial estimates obtained from computer models. Official property loss estimates will not be available for several weeks. Standard homeowners and business insurance policies cover wind damage, but not flood damage, which is covered under policies written by the National Flood Insurance Program. Tropical Storm Isidore, which came ashore in almost the same area of Louisiana a week before Lili, cost an estimated $100 million in insured losses, the institute said. The institute also said that natural disasters have cost the insurance company $4 billion so far in 2002, compared with $7.5 billion for the whole of 2001. Louisiana has been declared a disaster area by President Bush. Rapid needs assessment teams -- consisting of federal and state emergency workers -- surveyed the damage at first daylight Friday, according to Jim Ballow of the Louisiana Office of Emergency Preparedness. The storm knocked power out of nearly 465,000 homes, but by late Thursday workers had restored power to nearly 58,000 homes, Ballow said. About 6,200 people had lost their phone service. The entire population of Vermilion Parish -- home to 55,000 people -- had no power, according to Maxine Trahan, a spokeswoman for neighboring Acadia Parish's Sheriff's Office. The most severe damage reports were coming from the parishes of Iberia and Acadia. Two people in Acadia were injured when a roof collapsed, a spokeswoman for the parish's emergency operations center said, and two utility workers suffered minor injuries when a wall of bricks fell on their car, a spokeswoman for the sheriff's office said. None of the injuries was life-threatening. A police officer in Pointe Coupee Parish, northwest of Baton Rouge, suffered minor injuries when a tree fell on his car. The Acadia Parish town of Crowley, replete with large, historic homes and old live oak trees, was hit especially hard, Trahan said. At one car dealer in the town all the windows of the showroom were blown out, she said. The storm snapped trees, ripped off roofs and shingles, knocked down traffic signs and cut down utility wires in New Iberia, a town of 34,000 in Iberia Parish. Lili even caused rare whitecaps on the town's normally peaceful bayou, said Mayor Ruth Fontenot. In Terrebonne Parish, on the Gulf coast, 25,000 people are displaced because of high water, said Federal Emergency Management Agency director Joe Allbaugh, who was preparing to head to the state. Allbaugh estimated 150,000 people in various coastal parishes were out of their homes. Two tornadoes touched down around noon in Lafayette Parish, said Lt. Ray Schexnider with the local emergency operations center. There were no reports of damage or injuries, he said. The storm also ripped the roof off a motel and caused some flooding, he said, but he added that the tidal surge was not as high as was feared. In all, nearly 900,000 people were covered by evacuation orders as Lili approached -- many of whom heeded the warning and sought refuge farther inland, Shenofsky said. | X16: https://web.archive.org/web/20260620002742/https://www.cnn.com/2002/WEATHER/10/05/lili/ | Y16: found | Z16: 594 | AA16: cnn.com | AB16: -6.27 | AC16: -2.5 | AD16: Left-leaning
A17: 11 | B17: 3 | C17: Tropical Storm Isidore (September 2002) | D17: Tropical Cyclone | E17: 20020925 | F17: 20020927 | G17: 2001 | H17: 1150 | I17: 5 | J17: AL,LA,MS | K17: 13,14,15,6,7,8,National | L17: http://www.cnn.com/2002/WEATHER/10/01/lili/index.html | M17: Lili strengthens, aims for U.S. - Oct. 1, 2002 - CNN | N17: Oct 2, 2002 ... That would put it about 200 miles west of where Tropical Storm Isidore made landfall a week ago in southeastern Louisiana. Mississippi Gov ... | O17: Trash | S17: FALSE | T17: This article is primarily about Hurricane Lili (October 2002), not Tropical Storm Isidore. While Isidore is briefly mentioned as a geographic reference point, the article does not substantively cover Isidore's impacts, damages, costs, or response. | U17: =IF(SUMPRODUCT(--ISNUMBER(SEARCH('National Domains'!$A$2:$A$48,L17)))>0,"Yes","No") | V17: =IF(COUNTIFS(Calibration!$A:$A,A17,Calibration!$B:$B,B17)>0,"Yes","No") | W17: Lili strengthens, aims for U.S. Category 2 hurricane expected to make U.S. landfall Thursday MIAMI, Florida (CNN) -- A hurricane watch was issued Tuesday along the coasts of Texas and Louisiana as Hurricane Lili moved past Cuba toward the Gulf of Mexico. At 11 p.m. ET, the powerful Category 2 storm's maximum sustained winds were near 105 mph, and forecasters expected it to strengthen over the next 24 hours. Category 2 hurricanes have top winds of 96-110 mph and are capable of considerable damage to piers, road signs, homes, trees and low-lying coastal areas "I don't have any doubt that it will become a major hurricane, and that means a Category 3 or above," National Hurricane Center Director Max Mayfield told CNN. A Category 3 storm has winds of 111-130 mph. A hurricane watch was issued from San Louis Pass, Texas, to the mouth of the Mississippi River, in Louisiana. A tropical storm watch was in effect from the mouth of the Mississippi to Pascagoula, Mississippi -- a region that includes New Orleans and Lake Ponchartrain, Louisiana. As of 11 p.m., Lili was centered about 135 miles north-northeast of the northeast tip of Mexico's Yucatan Penninsula, about 520 miles southeast of New Orleans. It was moving toward the northwest at 16 mph. Lili, the fourth hurricane of the 2002 Atlantic season, could threaten the Louisiana or upper Texas coasts by Thursday, forecasters predicted. That would put it about 200 miles west of where Tropical Storm Isidore made landfall a week ago in southeastern Louisiana. Mississippi Gov. Ronnie Musgrove declared a state of emergency and mobilized the National Guard Tuesday. "Our first priority is the safety and security of the people of the state of Mississippi," Musgrove said in a statement. "By issuing the state of emergency now, we can put state resources in place to make sure that the needs of our citizens are met." NASA canceled the Wednesday's scheduled launch of Atlantis and said the space shuttle would take off no sooner than Thursday. NASA said it is most concerned with the storm passing near its Houston headquarters, not Kennedy Space Center in Florida, where the shuttle is to take off. Thousands could lose homes The storm caused heavy damage as it passed over western Cuba, cutting electricity and blocking roads. Residents in some areas could be contacted only by HAM radio. One death was reported. Schools were closed. Train service and flights were canceled. Authorities expected flooding in the south coastal part of Havana province and in the city of Havana itself. They warned that the biggest danger is the collapse of old and dilapidated buildings that are home to about 4,000 people. About 200,000 people were reported to have been evacuated, including more than 100,000 from the province of Pinar del Rio. More than 80,000 animals were taken to higher ground. Cuba discontinued hurricane warnings Tuesday evening and forecasters said the threat of storm surge flooding was decreasing. Earlier, the hurricane hit the same areas that were drenched last week by Hurricane Isidore, including the Cayman Islands and Cuba's Isle of Youth, where one gust was reported at 108 mph. Meanwhile, Kyle strengthened back into a tropical storm after being downgraded to a tropical depression earlier Tuesday. Kyle, with 50 mph sustained winds, was meandering about 270 miles south-southwest of Bermuda. Little motion and no significant change in strength were expected over the next 24 hours, forecasters said. Bermuda lifted a tropical storm warning. -- CNN Correspondent Lucia Newman contributed to this report. | X17: http://web.archive.org/web/20210608234647/http://www.cnn.com/2002/WEATHER/10/01/lili/index.html | Y17: found | Z17: 586 | AA17: cnn.com | AB17: -6.27 | AC17: -2.5 | AD17: Left-leaning
A18: 11 | B18: 4 | C18: Tropical Storm Isidore (September 2002) | D18: Tropical Cyclone | E18: 20020925 | F18: 20020927 | G18: 2001 | H18: 1150 | I18: 5 | J18: AL,LA,MS | K18: 13,14,15,6,7,8,National | L18: https://www.washingtonpost.com/archive/politics/2002/10/03/500000-ordered-to-flee-as-lili-nears-gulf-coast/858d3b42-aa47-435e-8a0e-ebc69afd9872/ | M18: 500000 Ordered to Flee As Lili Nears Gulf Coast | N18: Oct 2, 2002 ... It is potentially far more destructive than last week's Tropical Storm Isidore. Forecasters upgraded Lili to a Category 4 hurricane, the ... | O18: Trash | S18: FALSE | T18: Backfilled from Calibration sheet's LLM code -- this article was part of the 50-article human/LLM calibration sample and was intentionally skipped by the full-sample coding pass to avoid double-coding/double-cost. See Calibration sheet for the original human vs. LLM comparison and reliability stats. | U18: =IF(SUMPRODUCT(--ISNUMBER(SEARCH('National Domains'!$A$2:$A$48,L18)))>0,"Yes","No") | V18: =IF(COUNTIFS(Calibration!$A:$A,A18,Calibration!$B:$B,B18)>0,"Yes","No") | W18: NEW ORLEANS, Oct. 2 -- -- Nearly 500,000 residents of coastal Louisiana and Texas were told to evacuate today as the Gulf Coast braced for Hurricane Lili, a storm intensifying in strength as it aimed for a region still recovering from a tropical storm a week ago. Lili was surging up from the Caribbean today with 140-mph winds and was expected to make landfall Thursday morning. It is potentially far more destructive than last week's Tropical Storm Isidore. Forecasters upgraded Lili to a Category 4 hurricane, the second most powerful. It has already killed seven on Jamaica and St. Vincent and forced thousands of Cubans to flee their homes. "This has the potential to kill hundreds," said Max Mayfield, director of the National Hurricane Center in Miami. "Damage is going to be extensive. You better not get too close to this one." In the coastal area straddling Texas and Louisiana, weary residents still cleaning up from last week's $100 million in damage boarded up windows, sand-bagged doors, and braced for potential devastation. A hurricane warning extended from east of High Island, Tex., to the mouth of the Mississippi River in southeastern Louisiana. "We're getting ready for the real thing," said Ruth Fontenot, the mayor of New Iberia, a Cajun town in Louisiana's rice and sugar region, and a near bull's-eye in the storm's projected path. "It's increasingly gloomy in New Iberia." Fearful of a "catastrophic" potential 20-foot storm surge that would inundate the picturesque regional capital 140 miles west of New Orleans, she had just ordered the evacuation of all 35,000 citizens, and sent her own children out of town. New Iberia is only 10 miles from Vermilion Bay, which opens into the Gulf of Mexico. "The message I've been sending out is, 'Leave,' " Fontenot said. New Orleans, at the storm's projected eastern edge, remained calm today though area schools were to be closed Thursday, City Hall was ordered shut except for "essential" personnel, and Mayor Ray Nagin urged residents to stay close to home. "This is a very, very potent storm," Nagin said. Wind gusts of 30 to 40 mph were buffeting the city tonight. New Orleans was battered by heavy rain last week and suffered some flooding but quickly recovered thanks to its battery of 22 heavy pumping stations. States of emergency were declared in Louisiana and Texas. In Texas, officials urged 250,000 people in the Beaumont-Port Arthur area and 80,000 in Orange County to go inland, including 3,000 prisoners who were moved to jails away from the coast. Coastal ports in Louisiana that handle substantial percentages of the nation's oil imports were shut down. NASA's Mission Control in Houston was shut down, postponing today's scheduled space shuttle launch at Cape Canaveral, about 900 miles away. It was the first time in 41 years of manned space flights that bad weather in Houston prevented a Florida launch. In wild and marshy Cameron Parish, on Louisiana's sparsely populated southwestern coast, nearly the entire population of 10,000 people had been evacuated by this afternoon. "We're definitely going to get something out of this one," said sheriff's deputy Ed Racca. But he said residents had remained calm through the first evacuation in 10 years. "The older folks are used to this kind of stuff," Racca said. Roads north of Cameron Parish were reported clogged with heavy traffic. In Creole, a few miles from the gulf, "Everyone's pretty much gone," Michelle Trahan said this afternoon. "It's very quiet, very deserted," she said. She was waiting for her husband, a Cameron Parish police juror (county commissioner) to finish boarding up houses, before leaving herself. In New Iberia, residents and city workers worked feverishly throughout the afternoon at sand-bagging doors. "We're going to make it," said Fontenot, the mayor. "It's just not going to be very pleasant." | X18: https://archive.ph/BDyIp#selection-381.0-418.0 | Y18: found | Z18: 634 | AA18: washingtonpost.com | AB18: -7.01 | AC18: -2.5 | AD18: Left-leaning
A19: 12 | B19: 1 | C19: Eastern Tornadoes and Severe Storms (November 2002) | D19: Severe Storm | E19: 20021109 | F19: 20021111 | G19: 1252.8 | H19: 720 | I19: 28 | J19: CT,DE,FL,GA,MA,MD,ME,NC,NH,NJ,NY,PA,RI,SC,VA,VT,WV | K19: 1,2,3,4,5,6,National | L19: https://www.capecodtimes.com/story/news/2002/11/12/deadly-winds/50957526007/ | M19: Deadly winds - Cape Cod Times | N19: Nov 12, 2002 ... Residents of Mossy Grove, Tenn., sift through the wreckage left by a tornado. Savage rash of twisters slices across U.S., killing at least 35 ... | O19: Relevant | P19: 0 | Q19: C | S19: FALSE | T19: Backfilled from Calibration sheet's LLM code -- this article was part of the 50-article human/LLM calibration sample and was intentionally skipped by the full-sample coding pass to avoid double-coding/double-cost. See Calibration sheet for the original human vs. LLM comparison and reliability stats. | U19: =IF(SUMPRODUCT(--ISNUMBER(SEARCH('National Domains'!$A$2:$A$48,L19)))>0,"Yes","No") | V19: =IF(COUNTIFS(Calibration!$A:$A,A19,Calibration!$B:$B,B19)>0,"Yes","No") | W19: Savage rash of twisters slices across U.S., killing at least 35 Tennessee, Alabama worst hit search for missing continues Violent storms, including more than 70 tornadoes, blew across the nation early yesterday, slashing through small towns, splintering buildings and trees, twirling semi-trucks and cars and killing at least 35 people in a swath that stretched from the Gulf of Mexico to the Great Lakes. Starting late Saturday, the storms' fury mounted and swept from Louisiana, through Mississippi, Alabama, Tennessee and Ohio into Pennsylvania. early yesterday morning, the winds had demolished more than half of the two dozen houses that made up Mossy Grove, Tenn., a hamlet 40 miles west of Knoxville. Officials estimated more than a third of the structures were destroyed in Carbon Hill, Ala., a town of 2,071 people northwest of Birmingham. The deaths were most numerous in Tennessee where 16 people died, including seven in Mossy Grove. Another 12 were killed in Alabama, including seven in Carbon Hill. Five died in Ohio and one each in Mississippi and Pennsylvania. More than 200 people were injured. It was the deadliest swarm of tornadoes the nation has suffered since 1999 when at least 70 twisters killed more than 45 people over two days in Kansas and Oklahoma. Some places had only a few minutes' notice before the tornadoes swirled into town. In Van Wert, Ohio, that was just enough time to save dozens of people at the local movie theater. A manager heard a weather report on the radio as showings of "The Santa Clause 2" and "My Big Fat Greek Wedding" were ending and herded customers into hallways and restrooms - three cars blew into the theater and the roof collapsed on the blue-cushioned seats. "It wiped out three factories," said Larry Blakeley, 53, who lives about two miles from where the tornado touched down in Van Wert. "We had high winds and lightning. There are police cars and National Guard and you can't get close to where it happened." Radio pleas to the missingThe hardest-hit section in Tennessee included a five-mile stretch of Morgan County, which includes Mossy Grove. Rescuers spent yesterday combing through the wreckage. As the day ended, dozens of people were still missing. Local radio stations read the names of the missing over the airways and asked them to contact authorities if they heard their names. In some areas, phone calls on the lines that were working were so jammed that calls were not going through. Authorities were confident most people had fled their homes to safet would be accounted for soon. Still, the search was complicated by the devastation. "Emergency crews are out searching for people," said Amy Smith, a police dispatcher in nearby Oliver Springs. But she added, "The phone lines are down. They're without electric. It's going to be that way for a while." Officials from the Red Cross and emergency management teams spread out to assess the damage, and to provide those left homeless with food and shelter. In Alabama, Gov. Don Siegelman said it would take residents a long time to recover. "It's like somebody wrapped up sticks of dynamite and just blew these homes into little tiny pieces," Siegelman told reporters as he toured affected areas. "Clearly we've got to get money to these communities. But it's not so much the financial help at this point but the spiritual help that they need. We're going to do everything we can to get their lives, their homes back together." Winds hit an estimated 140 mph in Tennessee with torrential rain and golf-ball-size hail. The volatile weather was caused by unseasonably high temperatures, followed by a cold front pushing down from the north, creating optimal conditions for tornadoes, said Mark Linhares, a National Weather Service meteorologist based in Birmingham. Rare widespread twistersThe breadth of the storms was reminiscent of a similar tornado outbreak in November 1992 when a string of tornadoes sprang up in Texas and moved northeast. Ninety-four tornadoes resulted and 26 people were killed, 15 of them in Mississippi. But such widespread outbreaks are not common. In Alabama, nine people died in Walker County as a line of thunderstorms packing high winds and spinning off tornadoes rolled through the northern part of the state. In Georgia, heavy damage was reported near the town of Tate, about 45 miles north of Atlanta. In Tennessee, the tornadoes came in two waves. Late Saturda early Sunday, twisters skipped across western and middle Tennessee, killing three people. On Sunday night another line of storms crossed the state - this time south and east of Nashville. Two people, including a 10-year-old boy, were killed and 15 people were injured in Coffee County when two mobile home parks, three houses and a church were damaged near Manchester, about 60 miles southeast of Nashville, on Sunday night. | X19: http://web.archive.org/web/20260620003052/https://www.capecodtimes.com/story/news/2002/11/12/deadly-winds/50957526007/ | Y19: found | Z19: 802 | AA19: capecodtimes.com | AD19: Unidentified
A20: 13 | B20: 1 | C20: Western Fire Season (Fall 2002) | D20: Wildfire | E20: 20020901 | F20: 20021130 | G20: 2301.8 | H20: 1322.8 | I20: 21 | J20: AK,AZ,CA,CO,HI,ID,MT,NM,NV,OR,UT,WA,WY | K20: 15,16,17,18,National | L20: https://edition.cnn.com/2002/US/08/30/hln.hot.earth.wildfires/index.html | M20: Logging not the answer to wildfires residents say - September 2, 2002 | N20: Sep 2, 2002 ... All parties agree that seven years of drought in the West have resulted in the worst wildfire season in U.S. history. At issue is what can ... | O20: Relevant | P20: -1 | Q20: D | R20: other_human_causes | S20: FALSE | T20: The article covers the 2002 Western wildfire season (Arizona and broader West, September 2002), squarely within the event window and affected states. All parties in the article — including the Sierra Club — attribute the fires to forest management failures (fire suppression, commercial logging) and multi-year drought, with no mention of climate change or global warming as a contributing factor; the causal framing centers exclusively on human land-management decisions and natural drought cycles. | U20: =IF(SUMPRODUCT(--ISNUMBER(SEARCH('National Domains'!$A$2:$A$48,L20)))>0,"Yes","No") | V20: =IF(COUNTIFS(Calibration!$A:$A,A20,Calibration!$B:$B,B20)>0,"Yes","No") | W20: (CNN) -- Returning home after the wildfires, a frustrated homeowner in Arizona pointed to her burned land and lashed out at environmentalists. "We kept saying, if you don't do something, if you don't listen to us and fix this and address this you're not gonna have habitat for your frickin' spotted owl. I just wish that these environmentalists would just come to the ranch now and let me rub their noses in this ashtray they've left us," said Deborah Brimhall. But environmental groups are angry that they're being blamed for a problem they say was created by poor forest management. Sierra Club Executive Director Carl Pope said, "Scientists have determined these fire problems stem from three problems: nearly a century of fire suppression that removed the natural role fire plays in healthy forests, an extreme multi-year drought and decades of commercial logging that removed large, fire-resistant trees." He said, "For years the Sierra Club has been urging the Forest Service to do more prescribed burning, to reduce flammable brush near threatened communities, and we've been asking Congress to devote more money to do the job right." But Fire Information Officer Jim Paxon says there's plenty of blame to go around. He points out that many homeowners oppose preventive burning in their communities. "I think everybody that has anything to do with the management of these lands has part of the blame. Now you can go to the Forest Service and the Bureau of Land Management and the other land management agencies that were active in suppression [of naturally occurring forest fires] in a good spirited but misguided ecological standpoint. ...we're playing catch-up." But he adds, "We can put some of the blame on homeowners that don't wanna see smoke because they come up here to get away from the heat and the smog. You can put some on the environmentalists who want to stop us for doing our management activities because they disagree with us." All parties agree that seven years of drought in the West have resulted in the worst wildfire season in U.S. history. At issue is what can be done to develop more effective policies. President Bush wants to change forest management laws and allow timber companies to remove more trees from federal lands. But environmental groups say the president is just trying to help friends in the timber business. They say logging doesn't stop wildfires. | X20: http://web.archive.org/web/20180504012741/http://edition.cnn.com/2002/US/08/30/hln.hot.earth.wildfires/index.html | Y20: found | Z20: 399 | AA20: edition.cnn.com | AD20: Unidentified
A21: 13 | B21: 2 | C21: Western Fire Season (Fall 2002) | D21: Wildfire | E21: 20020901 | F21: 20021130 | G21: 2301.8 | H21: 1322.8 | I21: 21 | J21: AK,AZ,CA,CO,HI,ID,MT,NM,NV,OR,UT,WA,WY | K21: 15,16,17,18,National | L21: http://www.cnn.com/2002/US/09/01/california.fire/index.html | M21: Wildfire threatens holiday weekend campers in California - CNN | N21: Sep 1, 2002 ... She advised people in the forest to take State Highway 2 either east toward Wrightwood or west toward Chilao. ... August 30, 2002 • Wind ... | O21: Relevant | P21: 0 | Q21: C | S21: FALSE | T21: The article covers a wildfire in the Angeles National Forest, California, on September 1, 2002, which falls within the event window and affected state. The reporting is purely operational — fire size, evacuations, firefighting response — with no discussion of climate change or any other causal attribution. | U21: =IF(SUMPRODUCT(--ISNUMBER(SEARCH('National Domains'!$A$2:$A$48,L21)))>0,"Yes","No") | V21: =IF(COUNTIFS(Calibration!$A:$A,A21,Calibration!$B:$B,B21)>0,"Yes","No") | W21: RIVERSIDE, California (CNN) -- A fire that started Sunday afternoon in the Angeles National Forest had grown to 3,000 acres by the evening, and authorities rushed to evacuate campers from the popular recreation spot on the long holiday weekend. "It's burning in heavy brush and timber, and it's burning in a canyon uphill," said Mary Bowman, a U.S. Forest Service spokeswoman. "The prevailing winds are pushing it uphill. It's kind of like a chimney." The mouth of the San Gabriel Canyon faces the Pacific Ocean, and the afternoon ocean breeze was fanning the flames, she said. The fire was first reported at 12:34 p.m. (3:34 p.m. ET) Sunday, and five hours later it had grown to 3,000 acres, she said. But there were no reports of injuries. "The L.A. County Sheriff's Office is trying desperately to get people out of there," Bowman said. There are a number of campgrounds and picnic areas in the forest, just north of the greater Los Angeles area, which are popular recreational areas. A big concern is that the fire is burning on both sides of San Gabriel Canyon Road, the main road out of the forest in that area, she said. She advised people in the forest to take State Highway 2 either east toward Wrightwood or west toward Chilao. More than 200 recreational cabins are in the threatened areas, she said. The wildfire has burned some structures, Bowman said, but she did not know how many or what type they were. The cause of the fire was not yet known. Twenty aircraft were already fighting the flames from the air, she said, and orders went out for more than 100 firefighters. Mandatory evacuation orders were in place for the following areas: Coldbrook Campground, Fawnskin Picnic Area, Crystal Lake Campground, Deer Flats Campground, and Little Jimmy Campground. "We are asking that everyone who doesn't have to be there please stay out of the area," Bowman said. | X21: https://web.archive.org/web/20260620003408/https://www.cnn.com/2002/US/09/01/california.fire/index.html | Y21: found | Z21: 322 | AA21: cnn.com | AB21: -6.27 | AC21: -2.5 | AD21: Left-leaning
A22: 14 | B22: 1 | C22: U.S. Drought (Spring-Fall 2002) | D22: Drought | E22: 20020301 | F22: 20021130 | G22: 16031.6 | H22: 9006.4 | I22: 0 | J22: NATIONAL | K22: National | L22: https://www.cnn.com/2002/WEATHER/07/22/us.drought/index.html | M22: Far-reaching drought chokes much of U.S. - July 22, 2002 - CNN | N22: Jul 22, 2002 ... The last major drought in the United States occurred in the late 1980s and had an estimated economic impact of nearly $40 billion. The ... | O22: Relevant | P22: 0 | Q22: C | S22: FALSE | T22: Backfilled from Calibration sheet's LLM code -- this article was part of the 50-article human/LLM calibration sample and was intentionally skipped by the full-sample coding pass to avoid double-coding/double-cost. See Calibration sheet for the original human vs. LLM comparison and reliability stats. | U22: =IF(SUMPRODUCT(--ISNUMBER(SEARCH('National Domains'!$A$2:$A$48,L22)))>0,"Yes","No") | V22: =IF(COUNTIFS(Calibration!$A:$A,A22,Calibration!$B:$B,B22)>0,"Yes","No") | W22: (CNN) -- Four years without adequate rainfall have left a broad quilt of browned lawns, withered crops and scorched forests across much of the United States. But for Jeff Tranel, an agriculture and business economist with the Colorado State University extension service, it's what's not there that indicates how tough things are. "I'm out in the country quite a bit, and there are very few cows left," Tranel said recently. "In one county, Huerfano County, the 1997 census of agriculture data showed 28,000 beef cows in that county. A month ago, talking to ranchers, they said if you could find 1,000 to 5,000 cows, you would be lucky." The disappearance of thousands of cows from the heart of cattle country is a symptom of the severe drought that has gripped most of the West and much of the Southeast for four years. With nearly half the continental United States suffering from extremely dry conditions, some observers say it's the worst dry spell the country has seen in a generation -- perhaps two. "This drought is widespread and pretty intense over some large areas that rival those of the '50s," said Mark Svoboda, a climatologist at the National Drought Mitigation Center in Lincoln, Nebraska. "What we haven't seen maybe is the long-term heat, year after year after year, that we saw in the '30s." The effects have been seen most dramatically in Colorado, New Mexico and Arizona, where kiln-dry timberland exploded into a string of wildfires. More than 3.2 million acres have been burned this year, roughly twice the 10-year average, federal fire officials report. The U.S. Department of Agriculture has declared the entire state of Utah and numerous counties in Colorado, California, New Mexico and Arizona agricultural disaster areas, making farmers and ranchers in those regions eligible for federal emergency loans. The department also has opened millions of acres across 18 states from its Conservation Reserve Program for grazing and hay harvesting as ranchers have been forced to sell entire herds of cattle at a loss rather than keep them on drought-stricken pastureland. The last major drought in the United States occurred in the late 1980s and had an estimated economic impact of nearly $40 billion. The economic impact of the current drought differs among regions and sectors, Svoboda said, "but I think it's safe to say when it's all said and done, this one is going to be right up there. When we start looking at all the impacts, it's going to be in the billions of dollars." After years of drought in the Southwest and the Rockies, the High Plains states are starting to feel the pinch as well. In South Dakota, rainfall is about half of normal for much of the state, said Michael Held, administrative director for the South Dakota Farm Bureau. "In the central third of the state, most of the crops -- wheat as well as corn and soybeans -- have been severely damaged to completely ruined," he said. The drought is also causing problems for some of the fastest-growing cities in the increasingly urbanized Sunbelt, from Atlanta to Albuquerque. In New Mexico and southwestern Texas, only about 2 percent of the water that normally flows into Rio Grande has reached the river this year, said Barry Wirth, a spokesman for the U.S. Bureau of Reclamation. Along the Colorado River, which feeds some of the West's biggest cities -- including Las Vegas, Phoenix and Los Angeles -- water levels in major reservoirs like Lake Powell and Lake Mead are 50 to 60 feet below normal, Wirth said." It appears that we are on track right now to be equal to or worse than 1977, which was the worst drought year on record since Lake Powell was created. So we are in pretty stricken shape right now," he said. Residents of many of these cities are struggling with restrictions on water use even as more and more people are moving in. In Georgia, all 15 counties in metropolitan Atlanta are under water restrictions that allow outdoor watering only from 10 p.m. to 10 a.m. on alternate days. Lake Lanier, the major source of water for the area's nearly 4 million people, has been down as low as 12 feet below full pool in recent years: It is currently about 7 feet below normal. "We're only releasing the minimum flows necessary to preserve water quality in the system and water supply where needed," said Pat Robbins, a spokesman for the Army Corps of Engineers. "In other words, we've got it down to the absolute minimum that we can do, but we've got to maintain water quality and supply where it's needed." In Denver, city officials patrol enforce limits that allow homeowners to water lawns only every third day. Penalties range from a warning for first offenders to a $250 fine and the ultimate sanction -- having water cut off. "Our major job is to educate our customers on what they need to do," said Robert Trujillo, a member of the city's "Sod Squad." "Mostly, people understand. I haven't had anyone get really angry with me." The prospects for the future are uncertain. What forecasters are banking on to relieve the drought is the development of the recurring Pacific weather system known as El Nino. Scientists announced earlier this month that the phenomenon -- an above-average warming of eastern Pacific waters that typically occurs every four to five years -- should ease drought conditions in the Southeast and give the northern United States a mild winter. But continued concern can be seen in the picturesque snows atop the peaks of the Rockies. Mountain snowpacks serve as natural reservoirs that provide much of the next season's water supply for the West -- are currently between 25 percent to 40 percent of what observers consider normal, Svoboda said. "What's going be the real kicker is what happens this winter," Svoboda said. "Is this El Nino going to develop? It looks like it is, but is it going to be very strong? No, it doesn't look like it's going to be very strong. I think the jury's still out as to how beneficial this El Nino is going to be." The drought patrol, also known as the "Sod Squad," seeks out violations of water restrictions in Denver. | X22: https://web.archive.org/web/20260620003557/https://www.cnn.com/2002/WEATHER/07/22/us.drought/index.html | Y22: found | Z22: 1047 | AA22: cnn.com | AB22: -6.27 | AC22: -2.5 | AD22: Left-leaning
A23: 14 | B23: 2 | C23: U.S. Drought (Spring-Fall 2002) | D23: Drought | E23: 20020301 | F23: 20021130 | G23: 16031.6 | H23: 9006.4 | I23: 0 | J23: NATIONAL | K23: National | L23: https://www.nytimes.com/2002/03/15/us/drought-leaves-maine-stoic-but-struggling.html | M23: Drought Leaves Maine Stoic but Struggling - The New York Times | N23: Mar 15, 2002 ... ... us/drought-leaves-maine-stoic-but-struggling.html. Share full article ... Lent, district chief for the United States Geological Survey. | O23: Relevant | P23: 0 | Q23: C | S23: FALSE | T23: The article is clearly about the Spring 2002 Eastern Seaboard drought, covering specific impacts in Maine (well failures, water shortages, rural hardship) within the event window. There is no mention of climate change, global warming, natural variability, or any causal framing — it is pure event reporting focused on human impacts and expert observations about water levels. | U23: =IF(SUMPRODUCT(--ISNUMBER(SEARCH('National Domains'!$A$2:$A$48,L23)))>0,"Yes","No") | V23: =IF(COUNTIFS(Calibration!$A:$A,A23,Calibration!$B:$B,B23)>0,"Yes","No") | W23: Supported by Drought Leaves Maine Stoic but Struggling In a cluster of 40 homes near huge Sebago Lake, whose waters are spookily low and wearing a dismal late-winter collar of mud, residents have enough water in their wells to shower every other day -- and they shower fast. They flush their toilets once a day. Unable to use washing machines in their homes for the past five months, they wait in long lines at coin-operated laundries. For supper, they usually eat sandwiches off paper plates. If they want a proper meal -- the kind that requires washing a lot of dishes -- they drive to a restaurant. What little groundwater seeps into their wells is often contaminated. The foul stuff that is intermittently on tap at the home of Wendy Hurley, 34, a professor of sports medicine at the University of Southern Maine, has made her, her dogs and her cats sick. Dr. Hurley said it was killing her houseplants. Since last fall, she and her neighbors have been forced not only to drink bottled water, but to cook and brush their teeth with it, too. A record-setting drought along the Eastern Seaboard, which has raised alarms that water shortages will make life miserable all summer long, has been making life miserable in rural Maine all winter. The Maine Emergency Management Agency says it believes that many of the 53,000 households in the state that depend on shallow wells are running low on water. If exceptional rains do not come for several consecutive months this spring, experts agree, widespread hardship could lead to a health crisis for tens of thousands of rural residents. Continued severe drought could also cripple the tourist season, which triples water usage in many small lake and coastal communities. Determining the extent of the suffering has been difficult because the people of Maine are not prone to complaining. ''We think there are a lot of people out there not letting anybody know they are in trouble,'' said Lynette Miller, a senior planner at the emergency management agency. ''I attribute a lot of it to the stoicism of Maine. They feel that if they hang on long enough, it will rain.'' Normally, that would make sense. Maine is usually a very wet place, especially in the winter. The state gets more than three and a half feet of precipitation in a typical year, much of it in the form of snow. Winter usually refills Maine's 6,000 lakes and adequately supplies groundwater to the 280,000 houses that depend on wells or springs. Even after the driest of years -- last year was the driest of the 108 on record -- hydrologists say that a Maine winter can be counted on to help reset the water clock. But something scary happened over the last six months, said Robert A. Lent, district chief for the United States Geological Survey. Maine entered the winter with groundwater at dangerously low levels -- and as the long, dry, warmish winter slouches toward spring, they keep going lower. Against all experience, winter has made the drought worse. ''We have been setting record lows for groundwater almost every day for quite a while,'' Mr. Lent said. ''We have had really low water for over two years now.'' The consequences of low water are popping up all over Maine. Construction of many new homes has been postponed. Farmers are selling cattle. Small-town water districts will not allow fire departments to flush hydrants. Well-drilling companies are making money hand over fist, working seven days a week and unable keep up with demand. The average wait for a new well, which can cost $5,000 to $10,000, is about three months and lengthening. Many of the new wells are drilled to depths of 300 to 400 feet, replacing much shallower wells dug by backhoes. Schools, mobile home parks and a number of small towns are struggling to raise money for deeper wells, though there are no guarantees that new wells will yield safe water -- or any water at all. Like nearly every body of water in this state, Sebago Lake -- a trillion-gallon lake that is the second largest in Maine -- is about six feet below what is normal in the summertime. Boat ramps empty into mud flats. A ferry is mired in mud. Docks have collapsed at marinas, where there is not enough water to launch boats. Sebago Lake is the principal water source for 171,000 people in and around Portland, the state's largest city. The intake for the city's water system is near the bottom of the lake, and experts say that neither the supply nor the quality of water for Portland is likely to be affected by the drought. Most major towns in Maine also have secure water supplies, at least for the coming summer. For rural Mainers, though, hardships caused by wells running low are almost certain to get worse. Maine is the third-most-rural state in the nation, with 55 percent of its 1.3 million people living in rural areas. ''We have never been this low before, so who knows what is going to happen?'' said Tom Hawley, a hydrologist for the National Weather Service in Portland. ''We are going to see many, many more wells going dry this spring, unless we get several months of above-normal rains. I don't see that happening.'' Increased rainfall seems to be in store for some Eastern states, including Maine, the Weather Service said today. But it is not predicted to be enough to end the drought. Unlike many other states, Maine has few large aquifers to provide an insurance policy against long-term drought, said Mr. Lent at the Geological Survey. When winter betrays Maine, he said, there is little that anyone can do. For all the alarm one hears in the voices of water experts in Maine, Mainers themselves are not making much of a fuss. Few are clamoring for help from the government. Only 48 low-interest loans from the United States Department of Agriculture have been given to low-income Maine residents to drill new wells, although there is money available to help many more. Rather than complain to the government -- or to anyone, for that matter -- people here seem to be willing to wait out their problems. That is precisely the philosophy shaping the long, grim winter at the home of David and Diane Deering, who live in the woods of southern Maine, not from Hollis. ''It is kind of a Maine thing to bear up without saying anything,'' said Mrs. Deering, 57, a caseworker in the southern Maine office of Senator Olympia J. Snowe. ''You just kind of do what you have to do. We don't want to put money into a new well. We feel we can just persevere.'' The Deerings' well, which is 25 feet deep, went dry last October and their water pump burned out. The well had produced enough water during the past 30 years to raise three daughters, all of whom like long showers. So the Deerings decided to fix the water pump and do the Maine thing: Wait patiently for the well to produce water. It has, but only in a dribble. The Deerings have learned to live with it. They eliminated dish washing and laundry in the house. They take showers that last no longer than two minutes. They flush the toilet once a day. The Deerings' two oldest daughters are grown and showering elsewhere, so the burden of being a stoic teenage Mainer has fallen exclusively on their youngest, Emily, a high school senior. ''My parents are, like, O.K., we'll just wait it out,'' said Emily, who plays field hockey, basketball and lacrosse and whose showering requirements dwarf those of her parents. ''You try to keep it quiet at school that you are not taking as many showers as you'd like.'' She is surviving, Emily said, by showering at the home of friends with deeper wells. Advertisement | X23: http://web.archive.org/web/20220812232130/http://www.nytimes.com/2002/03/15/us/drought-leaves-maine-stoic-but-struggling.html | Y23: found | Z23: 1323 | AA23: nytimes.com | AB23: -8.02 | AC23: -2.5 | AD23: Left-leaning
A24: 14 | B24: 3 | C24: U.S. Drought (Spring-Fall 2002) | D24: Drought | E24: 20020301 | F24: 20021130 | G24: 16031.6 | H24: 9006.4 | I24: 0 | J24: NATIONAL | K24: National | L24: http://www.cnn.com/2002/WEATHER/08/14/drought.heat/index.html | M24: Drought grips much of U.S. - August 15, 2002 - CNN | N24: Aug 15, 2002 ... An extraordinary drought and near-record warm temperatures stretched across the United States in July, the National Oceanic and Atmospheric ... | O24: Relevant | P24: -1 | Q24: D | R24: natural_variability | S24: FALSE | T24: The article directly covers the Spring-Fall 2002 U.S. drought, reporting on its geographic extent, temperatures, and agricultural impacts within the event window. The only causal framing offered is the reference to a weak-to-moderate El Niño as a driver of elevated temperatures, with no mention of human-caused climate change — attributing conditions to natural variability. | U24: =IF(SUMPRODUCT(--ISNUMBER(SEARCH('National Domains'!$A$2:$A$48,L24)))>0,"Yes","No") | V24: =IF(COUNTIFS(Calibration!$A:$A,A24,Calibration!$B:$B,B24)>0,"Yes","No") | W24: CAMP SPRINGS, Maryland (CNN) -- An extraordinary drought and near-record warm temperatures stretched across the United States in July, the National Oceanic and Atmospheric Administration said Wednesday. NOAA's monthly drought assessment placed 49 percent of the contiguous United States in "moderate to severe" drought conditions -- due in part to the fifth-warmest July on record. Extreme drought conditions persisted across a huge swath of the West, from San Diego north to Montana, and east to Lincoln, Nebraska. Another extreme drought zone spread across the Southeast, from middle Georgia north to Delaware, while a third, smaller extreme drought zone gripped the lower Rio Grande Valley in Texas. For six U.S. states -- the Carolinas, Georgia, and Virginia in the east; Colorado and Wyoming in the west -- July wrapped up the driest August-to-July year in their history. Several Western states, struggling with arid pastures, range, and cropland, have been declared agricultural disaster areas by the U.S. Department of Agriculture. And the Forest Service is struggling with what has already been called one of the worst wildfire years in history: More than 4 million acres have burned, nearly twice the average year-to-date over the past decade. The NOAA's Climatic Data Center said average July temperatures this year were 2.2 degrees Fahrenheit higher than normal, making last month the fifth-hottest July since record-keeping began in 1895. Only the state of Texas bucked the trend. It had to cope with record floods in early July in what became the third-wettest July on record for the Lone Star State. Texas also was the only one of the 50 states whose temperatures were significantly below average. Thirty-nine states were warmer than average last month, according to NOAA. Climate researcher John Christy, of the University of Alabama at Huntsville, said 2002 is in line to be the second-hottest year in the past 20. He said the expected impacts of what NOAA predicts will be a weak to moderate El Nino weather phenomenon could drive average global temperatures higher in the final five months of the year. | X24: http://web.archive.org/web/20040822014827/http://www.cnn.com:80/2002/WEATHER/08/14/drought.heat/index.html | Y24: found | Z24: 339 | AA24: cnn.com | AB24: -6.27 | AC24: -2.5 | AD24: Left-leaning
A25: 14 | B25: 4 | C25: U.S. Drought (Spring-Fall 2002) | D25: Drought | E25: 20020301 | F25: 20021130 | G25: 16031.6 | H25: 9006.4 | I25: 0 | J25: NATIONAL | K25: National | L25: https://www.nytimes.com/2002/08/13/health/most-deadly-of-the-natural-disasters-the-heat-wave.html | M25: Most Deadly of the Natural Disasters: The Heat Wave | N25: Aug 13, 2002 ... Article on deadliest of natural disasters: heat wave; University of Delaware's Center for Climatic Research reports average of 1500 American ... | O25: Trash | S25: FALSE | T25: This article is a general feature about heat wave mortality in the U.S., focused primarily on the 1995 Chicago heat wave and historical events. It does not discuss the Spring-Fall 2002 U.S. drought event or any related 2002 disaster. | U25: =IF(SUMPRODUCT(--ISNUMBER(SEARCH('National Domains'!$A$2:$A$48,L25)))>0,"Yes","No") | V25: =IF(COUNTIFS(Calibration!$A:$A,A25,Calibration!$B:$B,B25)>0,"Yes","No") | W25: Supported by Most Deadly of the Natural Disasters: The Heat Wave Natural disasters usually come rife with drama. Hurricanes, tornadoes, forest fires, earthquakes -- all make for good headlines and even better visuals. But it would be hard to make a blockbuster movie about a heat wave. Heat waves come on subtly, raising summer temperatures just a little higher than normal and then receding. But they kill more people in the United States than all other natural disasters combined. The numbers are striking. According to the Center for Climatic Research at the University of Delaware, an average of 1,500 American city dwellers die each year because of the heat. Annual deaths from tornadoes, earthquakes and floods together total fewer than 200. The most deadly heat wave in recent years occurred in Chicago over a week in July 1995, when temperatures hovered around 100 degrees. Then, over 50,000 people were left without electricity, nearly two dozen hospitals closed their doors to new patients, ambulances lined up around the block waiting to drop off victims, and the county buried 68 people in a 160-foot-long trench. Though there was some argument over numbers, scientists now say that 739 people died that week. For context, the great Chicago fire of 1871 killed half that many. The San Francisco earthquake of 1989 killed 62, and Hurricane Andrew in 1992 killed 26. But even many of those who suffered through the 1995 heat wave failed to recognize its deadliness. ''When I interviewed Chicago residents, they usually remembered a death toll of about 100, and generally questioned whether the medical examiner had fabricated the figures or if the media had turned a nonevent into headline news,'' said Dr. Eric Klinenberg, a sociologist at New York University and the author of ''Heat Wave: A Social Autopsy of Disaster in Chicago.'' People find it hard to consider heat as a disaster for several reasons, Dr. Klinenberg says. First, heat waves cause little visible destruction. ''If a tornado touches down, the moment it hits, you can assess the damage,'' he said. With heat, at worst, roads buckle, trains derail and livestock die. Then there is the type of people heat waves kill. ''When there's a hurricane coming and there's valuable coastal property at risk, the whole world goes to watch,'' Dr. Klinenberg said. But in Chicago, as in other heat waves, the victims were ''the poor, the old, residents of abandoned and violent neighborhoods who lived alone, lacked access to transportation and lacked air-conditioning,'' he said. ''We're talking about people who are already out of sight.'' It is not easy to assess the number of deaths in a heat wave. In 1995, Chicago officials questioned whether the medical examiner's count of 525 was exaggerated; epidemiologists now say it was low. ''As a mathematician I did know whatever the medical examiner said would be undercounting it,'' said Dr. Steven Whitman, who was director of epidemiology for Chicago's Department of Public Health then. For each heat-related death, he said, the medical examiner must confirm one of three factors: a body temperature of 105 degrees or more, a high environmental temperature at the death scene, or decomposition in a body seen alive just before the heat wave. But since autopsies are not performed on all bodies, not all heat-related deaths are recorded. In addition, fatal strokes and heart attacks attended by physicians are generally not counted as heat-related deaths, even if they probably would not have occurred without the heat. For a more accurate picture, Dr. Whitman compared the number of deaths that month, around 3,000, with the expected number in an average month, 2,200, attributing the difference, or ''excess deaths,'' to the heat. Other deadly heat waves in the United States occurred in New York City in 1972, when 891 died; in Los Angeles in 1955, when 946 died; and across the Midwest in 1980, when hundreds were killed. Perhaps surprisingly, cities that suffer most in heat waves are not those in the hottest zones. ''A heat wave is a very relative factor,'' said Dr. Laurence S. Kalkstein, a climatologist at the University of Delaware Center for Climatic Research. ''What makes a heat wave in Duluth is not what makes a heat wave in Dallas. We respond to the normal weather conditions of wherever we live.'' A heat wave, as he defines it, is a variation from normal. Areas with irregular but intense variability, like New York or Chicago, where the temperature can vary by 20 degrees or more in a few days, fare worse than places like Phoenix or Miami, where the weather is warmer but more constant. ''In New York we once calculated a threshold of 93 degrees for a few days, whereas in Phoenix it might be 112,'' Dr. Kalkstein said. Other factors also come into play. Cities bake more intensely under sunny skies than under clouds. Humidity reduces the body's ability to perspire and cool down. Strong winds are more dangerous than still weather because they dry people out. Cities' structures also affect death rates. ''In Philly, which has more row houses than any other city, you've got black tar roofs, brick facades and windows on only two sides,'' Dr. Kalkstein said. ''In Baton Rouge, even the poorest of the poor have what they call shotgun shacks, which have aluminum roofs and windows on four sides,'' allowing more ventilation. It does not take a lot of extra heat to kill the vulnerable. ''The body works in a very small temperature range,'' said Dr. Lawrence Robinson, deputy health commissioner of Philadelphia. ''The body circulates blood to the skin and perspiration removes heat from the skin. In extreme heat, the heart has to pump faster and harder,'' leading to heart attacks or strokes. Even a healthy person who overexerts in the heat can die of heat stroke. Amid fears that global warming will usher in longer and more deadly heat waves, Dr. Kalkstein said weather variability was still more important. If variability in the United States increases or even stays constant, he added, heat deaths could increase from 1,500 to 3,900 by 2050. Just as high temperatures alone do not make a deadly heat wave, poverty alone does not make a heat wave deadly. In Chicago in 1995, a disproportionate number of victims were men living by themselves in single rooms. Nor did all poor communities suffer equally. One poor area with high rates of violence and abandoned buildings had a death rate 10 times as high as that of a similarly poor adjacent area with the same percentage of elderly, solitary residents but a more active street life. ''The areas of the city that had high concentrations of deaths are areas that had lost the viable public spaces, the busy sidewalks, the commercial streets,'' Dr. Klinenberg said. ''Those are the things that draw people out of their home and into social contact.'' Dr. Klinenberg sees the high death rate as a symptom of a problem that already exists in American cities, even when there is no heat wave. ''Heat waves are like urban particle accelerators,'' he said. ''They speed up and make visible conditions that are always there but are difficult to perceive. Living and dying alone is one of those conditions. When hundreds of people die alone and at home behind locked doors and sealed windows out of touch with their families and community support, it's a sign of sweeping social breakdown.'' In the past decade, some cities have mitigated the deadliness of heat waves with response systems that include news media warnings, lists of elderly residents who live alone, heat command centers, water trucks and door-to-door checkups of people at risk. Unlike some natural disasters, heat waves usually allow for some preparation time. ''Information about an oncoming heat wave is available as much as three days in advance, and they take two days to start killing,'' said Dr. Robinson of Philadelphia. Heat-related death rates there have been down since a warning system was introduced seven years ago by the Center for Climatic Research. Chicago, which took criticism for its response to the 1995 heat wave, has also improved its systems, to the point where a 1999 heat wave comparable in intensity to the one of 1995 killed only 110 people. Still, said Dr. Klinenberg, the heat disasters have not gone away. ''If that was an airplane crash, people would still be talking about it today,'' he said of the 1999 heat wave. ''Now, if you ask people, they don't even remember it.'' Related Content Advertisement | X25: http://web.archive.org/web/20251012091127/https://www.nytimes.com/2002/08/13/health/most-deadly-of-the-natural-disasters-the-heat-wave.html | Y25: found | Z25: 1418 | AA25: nytimes.com | AB25: -8.02 | AC25: -2.5 | AD25: Left-leaning
A26: 16 | B26: 1 | C26: Severe Storms/Tornadoes (May 2003) | D26: Severe Storm | E26: 20030503 | F26: 20030510 | G26: 7100.9 | H26: 4128.4 | I26: 51 | J26: NATIONAL | K26: National | L26: http://www.cnn.com/2003/WEATHER/05/12/tornadoes/ | M26: Alabama latest to be declared disaster - May. 12, 2003 - CNN | N26: May 12, 2003 ... If those preliminary numbers hold, they would constitute the worst tornado outbreak during a seven-day period in the United States -- in ... | O26: Relevant | P26: 0 | Q26: C | S26: FALSE | T26: The article directly covers the May 2003 severe storm/tornado outbreak, discussing impacts, disaster declarations, casualties, and damage across multiple affected states within the event window. There is no mention of climate change or any causal attribution beyond straightforward event reporting. | U26: =IF(SUMPRODUCT(--ISNUMBER(SEARCH('National Domains'!$A$2:$A$48,L26)))>0,"Yes","No") | V26: =IF(COUNTIFS(Calibration!$A:$A,A26,Calibration!$B:$B,B26)>0,"Yes","No") | W26: Alabama latest to be declared disaster WASHINGTON (CNN) -- President Bush on Monday declared a major disaster in Alabama following severe storms, tornadoes and flooding in the state, the White House said. The action makes federal funding available in 16 counties. Supercell thunderstorms on May 7 generated at least 10 tornadoes and record flooding in Alabama, according to the National Weather Service. Most of the damage was from Lamar County to the northern edges of Birmingham. The designation adds to the list of other states hit hard by tornadoes -- a list that already includes Missouri, Kansas, Tennessee and Oklahoma. Tennessee, Missouri, Oklahoma hit the hardest Officials with Tennessee Emergency Management Agency were shaking their heads in disbelief Monday after yet another round of tornadoes hit the state over the weekend, capping more than a week of storms. "It was astounding," agency spokesman Kurt Pickering said. "I haven't seen a weather event that's been as strung out as this one" in the five years he has been with the agency. "Somewhere inside the borders of Tennessee, there was a tornado warning" for five straight days starting May 4, Pickering said. The agency's director, who has been on the job well over 30 years, also did not remember anything like this, Pickering said. Pickering said storms and flooding have claimed 16 lives in the state, but no one was killed or seriously injured when Sunday's twisters tore through middle Tennessee. During the past eight days, more than 8,000 structures throughout the state were damaged or destroyed, he said. "Most are residences, but there are some churches, businesses and outbuildings" affected as well, Pickering said. Preliminary damage assessment teams of federal, state and local officials continued their work Monday in a number of counties. President Bush declared major disaster areas in Tennessee and Missouri, and added parts of Oklahoma to the list Saturday after back-to-back tornadoes there. Those states endured the largest number of tornadoes, according to preliminary figures from the National Oceanic and Atmospheric Administration. They join 16 others reporting 395 twisters during the period from Sunday, May 4 through Saturday, May 10. If those preliminary numbers hold, they would constitute the worst tornado outbreak during a seven-day period in the United States -- in terms of total number of tornadoes -- since NOAA began keeping records in 1950, said agency spokesman Joe Schaeffer. It would be more than double previous tornado numbers, Schaeffer said. Meanwhile, Missouri emergency officials reported improved weather conditions had given them the "opportunity to look around at some of the counties impacted over the weekend." "We had some pretty good storms going on Saturday," including a tornado in Lewis County, said Missouri Emergency Management Agency spokesman Jim Wakeman. The National Guard has been withdrawn from duty in the state as the cleanup continues, said Wakeman. Missouri's disaster field office is opening Monday in Springfield, he said. | X26: http://web.archive.org/web/20260620004115/https://www.cnn.com/2003/WEATHER/05/12/tornadoes/ | Y26: found | Z26: 480 | AA26: cnn.com | AB26: -6.27 | AC26: -2.5 | AD26: Left-leaning
A27: 16 | B27: 2 | C27: Severe Storms/Tornadoes (May 2003) | D27: Severe Storm | E27: 20030503 | F27: 20030510 | G27: 7100.9 | H27: 4128.4 | I27: 51 | J27: NATIONAL | K27: National | L27: http://edition.cnn.com/2003/WEATHER/05/06/tornadoes/index.html | M27: Tornado strikes eastern Missouri town - May. 6, 2003 - CNN | N27: May 7, 2003 ... ... tornado and this time a small town on the state's eastern edge bore the brunt of the damage it caused. The twister struck "numerous ... | O27: Relevant | P27: 0 | Q27: C | S27: FALSE | T27: The article directly covers the May 2003 severe storm/tornado outbreak affecting Missouri, Tennessee, Kansas, and other states within the event window (May 3–10, 2003), reporting on damages, casualties, and emergency response. There is no mention of climate change or any broader causal attribution — it is purely event and impact reporting. | U27: =IF(SUMPRODUCT(--ISNUMBER(SEARCH('National Domains'!$A$2:$A$48,L27)))>0,"Yes","No") | V27: =IF(COUNTIFS(Calibration!$A:$A,A27,Calibration!$B:$B,B27)>0,"Yes","No") | W27: Tornado strikes eastern Missouri town DE SOTO, Missouri (CNN) -- For the second time in three days, Missouri came under attack from a tornado and this time a small town on the state's eastern edge bore the brunt of the damage it caused. The twister struck "numerous buildings" in De Soto Tuesday night, police and sheriff's officials said, and caused the junior high school to collapse. "It's pretty disastrous," said Adam Sitton of the Missouri State Highway Patrol. He did not know of any injuries at the junior high. Jason Law, owner of J.P. Carson's Restaurant on North Main Street, said the storms came through town around 7 p.m. (8 p.m. ET) and were continuing two hours later. He said heavy rain caused about a foot of water to rush through Main Street like a river. "We've been pretty much cut off since about 7:30," he said. Law said a telephone pole with electrical lines had fallen onto the roof of a building in town, and trees were snapped. Large pieces of metal were impaled in the back of his restaurant, he said. "There has been a tragedy in De Soto," said a dispatcher for the town's fire department, without giving any details. De Soto, in Jefferson County and about 40 miles south of St. Louis in eastern Missouri, has a population of about 6,400. The National Weather Service issued a tornado watch and a flash flood warning for the county, in effect until midnight. A flood watch was also in effect. Seven counties in central Missouri and two counties in eastern Kansas experienced hail the size of golf balls and 70 mph winds Tuesday afternoon, said Rich Thompson, a lead forecaster with the National Weather Service. He said there were storms "with rotation" winds, which posed a threat of tornadoes. "One storm after another" lined up from west to east in Kansas, Oklahoma, Missouri, Arkansas and Louisiana, CNN Meteorologist Chad Myers said. The storms were expected to move into eastern Tennessee, Georgia, Alabama and Mississippi on Wednesday. Missouri seeks federal help in wake of Sunday's twisters Missouri Gov. Bob Holden declared a statewide emergency Monday and asked President Bush to declare dozens of counties federal disaster areas. Missouri officials revised the statewide death toll upward to 18, five of which were in the battered area around Pierce City which was hit by a twister Sunday. Tennessee Emergency Management Agency spokesman Cecil Whaley said Tennessee's death toll went up to 15, and Kansas remained at seven -- creating a total death toll of 40 people from Sunday's storms across the three states. Northeast Alabama and northern Georgia spent Tuesday under tornado warnings as bad weather moved through. In Georgia, tornadoes were spotted in Smyrna, just north of Atlanta, and in Bartow County and in northern Alabama. The threat moved quickly eastward into South Carolina, where tornado watches were issued, but the storm left heavy rains and flash floods in its wake. Earlier Tuesday, warnings were posted for Grundy and Coffee counties in southeast Tennessee, near where 15 people were killed in tornadoes Sunday night. A tornado was reported during a heavy storm at Meridianville, Alabama, north of Huntsville, but the damage was minor, said Scott Worsham from the Huntsville-Madison County Emergency Management Agency. Trees and power lines were knocked down in the county, and flash flooding and other wind damage were reported. Worsham said volunteer firefighters reported seeing the funnel. Tennessee town struggles to recover In Jackson, Tennessee, part of which was devastated by a tornado Sunday, Mayor Charles Farmer said 300 people were sheltered at a basketball arena. He said two people were missing in the town, and nine people were confirmed dead. There was to have been a mayoral election Tuesday in Jackson, but it was postponed. The structural integrity of bridges was a concern along secondary roads in a dozen counties where the rain has been the heaviest, said Whaley. Several more days of rain are forecast, Whaley said. Tennessee Gov. Phil Bredesen and U.S. Sen. Lamar Alexander were touring storm-damaged areas in Madison County. Sunday's tornado in western Tennessee was determined to be an F4 -- meaning winds topped 207 mph. It damaged about 1,600 homes and businesses, Whaley said. (Fujita scale) History destroyed in small town The sound of chain saws echoed through Pierce City, Missouri, a town of 1,400 that was littered with debris. Holden said as many as eight people were missing. CNN's David Mattingly reported that many of the town's old buildings will have to be torn down. The National Guard Armory, where 40 people sought shelter and one died, has blown-out windows and a collapsed roof. More than 80 twisters were sighted in central and Southeastern states Sunday evening, said Dick Hainje, a regional director of the Federal Emergency Management Agency. The National Weather Service will not know how many tornadoes touched down until a storm survey team has assessed and tracked the damage, said Dan McCarthy of the Storm Prediction Center. | X27: http://web.archive.org/web/20250911102200/https://edition.cnn.com/2003/WEATHER/05/06/tornadoes/index.html | Y27: found | Z27: 831 | AA27: edition.cnn.com | AD27: Unidentified
A28: 16 | B28: 3 | C28: Severe Storms/Tornadoes (May 2003) | D28: Severe Storm | E28: 20030503 | F28: 20030510 | G28: 7100.9 | H28: 4128.4 | I28: 51 | J28: NATIONAL | K28: National | L28: http://www.cnn.com/2003/WEATHER/05/08/tornadoes/index.html | M28: Tornado hits Oklahoma as storms batter Midwest - May. 8, 2003 - CNN | N28: May 8, 2003 ... CNN's Miles O'Brien recaps the storms that have rocked the midwest and southern U.S. premium content. PLAY VIDEO. Pierce City, Missouri, ... | O28: Relevant | P28: 0 | Q28: C | S28: FALSE | T28: The article directly covers the May 2003 tornado outbreak, reporting on specific storm impacts across Oklahoma, Kansas, Tennessee, Georgia, and Mississippi within the event window. There is no discussion of climate change or any other broader causal framing — only meteorological explanation (low-pressure system mixing heat and moisture) and event reporting. | U28: =IF(SUMPRODUCT(--ISNUMBER(SEARCH('National Domains'!$A$2:$A$48,L28)))>0,"Yes","No") | V28: =IF(COUNTIFS(Calibration!$A:$A,A28,Calibration!$B:$B,B28)>0,"Yes","No") | W28: Tornado hits Oklahoma as storms batter Midwest At least 125 injured OKLAHOMA CITY, Oklahoma (CNN) -- Another violent outbreak of tornadoes pummeled the Midwest Thursday, wreaking havoc from the suburbs of Oklahoma City northward to the towns of eastern Kansas. There were no reports of fatalities. At least one tornado swept through the Oklahoma City area Thursday evening, flattening several buildings. A General Motors plant in nearby Midwest City, Oklahoma, was hit along with a housing subdivision near Tinker Air Force Base, authorities said. In Thursday's storm, which closely followed the path of a deadly 1999 storm, the Oklahoma Civil Emergency Management, which collects and manages the reporting of data from local agencies, confirmed 73 injuries and no fatalities. The tornado appeared during rush hour, around 5 p.m. CT (6 p.m. ET) and traveled across two major interstates, dropping debris and crippling traffic, said George Johnson, a spokesman at the Oklahoma Emergency Operations Center. "Imagine the traffic jam you've got," Johnson said. "We're talking about several miles of debris going down the interstate." "There are vehicles tossed hither and yon just like throwing pick-up sticks," Albert Ashwood, the state director of emergency management, said the GM plant took a "direct hit." The plant was operating at the time but the extent of injuries inside was not immediately known. A plume of black smoke could be seen rising from the vicinity of the plant and power was knocked out to more than 26,000 residents in the Oklahoma City area. Oklahoma Gov. Brad Henry said damage to the plant would have a "significant impact on the state and its economy," but he vowed the state would rebound. "We'll be stronger in the end," he said. Michelann Ooten, an emergency management spokeswoman, said authorities were most concerned about people trapped in buildings and homes. "We may have people trapped in vehicles. We may have people trapped in trailers," she said. The National Weather Service issued a bulletin that said: "A large and violent tornado was located over southeast Midwest City, moving northeast at 35 mph. Homes and other large structures have already been flattened by this tornado." A dispatcher with the Cleveland County Sheriff's Office said the city of Moore, Oklahoma, suffered "extensive damage" when the tornado moved eastwards. State authorities said 300 homes were destroyed and 1,500 damaged. Video from the scene showed the sign to the McDonald's twisted into a mangled heap, with the windows of the restaurant blown out. A playground for kids at the restaurant had its tunnels twisted apart and its glass wall hung in pieces. Nearby homes and apartments had their roofs ripped off, trees were scattered across neighborhoods and power poles and lines were down in several areas. Earlier, a "very dangerous" storm system began moving across central Kansas with forecasters warning the storm would intensify throughout the night, spawning tornadoes and dumping baseball-sized hail in its wake. A tornado touched down in a field in Cloud County, Kansas, around 3:30 p.m., causing no major damage but putting authorities on alert. Officials recorded 225 tornadoes for the first seven days of May -- already a record number and the total continues to rise. More than 40 people have been killed in the non-stop storms. Forecasters said the violent storms were the result of a low-pressure system moving up from the southwest, mixing a lot of heat and moisture in the atmosphere. Areas that could be affected Thursday evening include eastern and central Kansas, western Missouri, northern Oklahoma and northern Arkansas. Many of those areas sustained major damage when tornadoes ripped through earlier this week. The death toll climbed higher Thursday morning when one person was killed in Georgia as floodwaters covered streets and delayed school openings. The Troup County sheriff's department said high water swept a car off a road about 7:45 a.m. EDT, killing the driver. The incident occurred less than an hour after the sheriff's department banned all traffic in the county except for emergency vehicles. Later in the afternoon, two tornadoes swooped down near Denver International Airport as severe thunderstorms barreled through the area. There were no reports of injuries and no damage was reported at the airport. In Chattanooga, Tennessee, school closings stretched into their third day Thursday with some 60 roads closed because of flooding. Authorities said the Tennessee River -- which had reached its highest levels in 30 years in recent days -- receded Thursday morning but was still about five feet above flood level. Maxwell said officials have estimated $10 million to $17 million worth of damage so far in the area. Three-hundred structures, including dozens of homes, have been affected, the Tennessee Valley Authority said. The area received as much as 8 inches in less than a day, swelling the creeks and tributaries that feed into the Tennessee river. Emergency personnel have reported no injuries or deaths directly related to the flooding, she said. In Mississippi, a day after Gov. Ronnie Musgrave declared a state of emergency, emergency management officials were working to "get a joint damage assessment team into the area, hopefully (Thursday)," spokeswoman Amy Carruth said. That team would have representatives from FEMA, local government officials, and Mississippi emergency management department personnel and would focus "primarily on Monroe and Chickasaw counties," Carruth said. | X28: https://web.archive.org/web/20260620004308/https://www.cnn.com/2003/WEATHER/05/08/tornadoes/index.html | Y28: found | Z28: 877 | AA28: cnn.com | AB28: -6.27 | AC28: -2.5 | AD28: Left-leaning
A29: 16 | B29: 4 | C29: Severe Storms/Tornadoes (May 2003) | D29: Severe Storm | E29: 20030503 | F29: 20030510 | G29: 7100.9 | H29: 4128.4 | I29: 51 | J29: NATIONAL | K29: National | L29: http://www.cnn.com/2003/WEATHER/05/09/tornadoes/index.html | M29: Flood waters rising as tornado threat persists - May. 9, 2003 - CNN | N29: May 9, 2003 ... A state trooper walks past the tornado-damaged offices of the United Auto Workers near the GM plant in Oklahoma City. | O29: Relevant | P29: 0 | Q29: C | S29: FALSE | T29: The article directly covers the May 2003 tornado outbreak, focusing on impacts in Oklahoma City/Moore, flooding in the Southeast, injuries, and damage — all within the event window. There is no discussion of climate change, global warming, or any other causal framing; it is pure event/impact reporting. | U29: =IF(SUMPRODUCT(--ISNUMBER(SEARCH('National Domains'!$A$2:$A$48,L29)))>0,"Yes","No") | V29: =IF(COUNTIFS(Calibration!$A:$A,A29,Calibration!$B:$B,B29)>0,"Yes","No") | W29: Flood waters rising as tornado threat persists More than 100 Oklahomans injured in Thursday storms OKLAHOMA CITY (CNN) -- Widespread flooding is causing new troubles for areas struck by this week's tornadoes and storms in the southeastern United States. Hundreds of people have fled their homes and businesses in Alabama, Georgia and Tennessee. Chattanooga, Tennessee, is suffering some of the worst flooding in years by the Tennessee River, the AP reports. West-central Georgia residents have evacuated to escape the rising Chattahoochee River. Meanwhile, Oklahoma City awoke Friday to hundreds of flattened and damaged buildings, including a General Motors manufacturing plant, after at least one tornado swept through the area, injuring more than 100 people. But even as cleanup efforts begin, weather forecasters warned of more treacherous storms. Conditions were expected to be clear during the day Friday, but with a significant risk of severe weather after midnight, according to CNN Meteorologist Chad Myers, who said tornadoes are difficult to see in the dark. For Oklahoma City and the surrounding area, Thursday's twister was a frightening reminder of a 1999 tornado that followed almost the same path, killing 47 people. "This town is in total shock this morning as they wake up," said American Red Cross spokesman Michael Spence. "This is the second time in four years this town has been devastated by a tornado." Oklahoma Gov. Brad Henry said Thursday's storm injured more than 118 people in the region and destroyed hundreds of buildings, but that figure could increase as crews assess the damage. Paul O'Leary, who was on scene with the Oklahoma City Ambulance Service, said at least 125 people were injured, about 12 of them seriously. Only minor injuries were reported at a General Motors plant in the tornado's path. Most of the damage was confined to the plant's painting facility, state officials said Thursday. A spokesman from Henry's office credited early weather reports for the lack of injuries in the plant. Paul Sund said most of the employees evacuated long before the tornadoes touched down, thanks to meteorologists' warnings. In the hardest hit suburb of Moore, Oklahoma, 300 homes were destroyed and 300 suffered minimal to moderate damage, said Sgt. Scott Singer of the Moore Police Department. In addition, 20 businesses were lost. Moore is located between Oklahoma City and Norman -- home to the University of Oklahoma -- on the south side of the metropolitan area. The governor's office said an official from the Federal Emergency Management Agency will survey the area Friday. Emergency officials secured the area Thursday night to prevent looters from coming in. "The storm hopped and skipped through the town," Singer said, noting the damage could have been much worse. "It hopscotched across the city. It didn't stay on the ground the whole time." Video from the scene showed the sign to a McDonald's twisted and mangled in a heap, with the windows of the restaurant blown out. The "Play Place," a playground for kids at the restaurant, had its tunnels twisted apart, and its glass wall hung in pieces. In one video shot, a car was seen on top of a house. The tornado also made a mark north in Osage County, located along the state line with Kansas. There were no injuries, but 21 cattle were downed by the storm in the farming town of Pawhuska, state officials said. Ten homes, a host of barns and one mobile home were destroyed there. Two mobile homes were damaged, officials said. Approximately 33,000 homes in Oklahoma City and Pawhuska were without power Friday morning, emergency officials said. The tornado appeared in Oklahoma City during rush hour, around 5 p.m. CT (6 p.m. ET) and traveled northeast across two major interstates, dropping debris and crippling traffic, said George Johnson, a spokesman at the Oklahoma Emergency Operations Center. "Imagine the traffic jam you've got," Johnson said. "We're talking about several miles of debris going down the interstates." Sections of Interstate 240, which circles Oklahoma City and crosses Interstate 35, were closed due to debris, he said. The tornado "flattened" a bank and a small hotel along I-240 near the General Motors Plant. Albert Ashwood, the state director of emergency management, said the plant took a "direct hit." A plume of black smoke could be seen rising from the vicinity of the plant. Henry said GM officials told him the state's early response system saved lives at the plant. The system was put in place after a series of killer tornadoes hit the region May 3, 1999. Forty-seven people died in those storms in Texas, Oklahoma and Kansas. Another 800 were injured. Ashwood, comparing the 1999 storm to this one, said the storm four years ago was more devastating in terms of casualties and property damaged. "Unfortunately, if your house was destroyed yesterday, it was the worst storm in history," he said. As Thursday's tornado crossed Interstate 35, it made its way into the city of Moore. Power poles and lines were down in several areas, and local news video showed the remains of a gas meter in someone's front yard, with its pipes twisted around it. A bulldozer went down one road pushing the piles of debris out of the way. "I heard this real loud roar," said one woman, a resident of Moore. "I did a 100-yard sprint over to my neighbor's house to get in her basement. We could just hear the two by fours splitting and the trees falling." Hundreds of trees and power lines littered the landscape for miles. On one farm, a horse stood outside a fence that had been shredded, looking almost as if he was inspecting the damage. The governor said an emergency declaration for federal assistance was in the works for Cleveland and Oklahoma counties, which will enable residents and businesses to rebuild. He is expected to do an aerial survey of the damage with the National Guard Friday morning. | X29: http://web.archive.org/web/20071211143458/http://www.cnn.com:80/2003/WEATHER/05/09/tornadoes/index.html | Y29: found | Z29: 984 | AA29: cnn.com | AB29: -6.27 | AC29: -2.5 | AD29: Left-leaning
A30: 16 | B30: 5 | C30: Severe Storms/Tornadoes (May 2003) | D30: Severe Storm | E30: 20030503 | F30: 20030510 | G30: 7100.9 | H30: 4128.4 | I30: 51 | J30: NATIONAL | K30: National | L30: http://www.cnn.com/2003/WEATHER/05/07/tornadoes/index.html | M30: CNN.com - States face new tornado forecast - May. 7, 2003 | N30: May 7, 2003 ... ... Severe weather continues to threaten the Southern United States. CNN's Aaron Brown reports. (May 7) premium content. PLAY VIDEO. Personal ... | O30: Relevant | P30: 0 | Q30: C | S30: FALSE | T30: The article directly covers the May 2003 tornado outbreak, reporting on the 135 tornadoes recorded, deaths, and storm impacts across multiple states within the event window. There is no discussion of climate change, global warming, or any other causal attribution — only pure event reporting on impacts, forecasts, and emergency response. | U30: =IF(SUMPRODUCT(--ISNUMBER(SEARCH('National Domains'!$A$2:$A$48,L30)))>0,"Yes","No") | V30: =IF(COUNTIFS(Calibration!$A:$A,A30,Calibration!$B:$B,B30)>0,"Yes","No") | W30: States face new tornado forecast 135 tornadoes recorded since Sunday CARROLLTON, Georgia (CNN) -- Severe thunderstorms rumbled across central Alabama and northern Georgia Wednesday night, uprooting trees, downing power lines and swamping areas already deluged by three straight days of heavy rains. And while the Southeast braced for another night of powerful storms, forecasters warned that conditions were ripe for Kansas, Missouri and Arkansas to be hit by more tornadoes Thursday. Those states were heavily damaged earlier this week in one of the most intense outbreaks of tornadoes in 53 years of record-keeping. Officials have recorded 135 tornadoes for the week since Sunday. More than 40 people have been killed in the non-stop storms. In Alabama and Georgia late Wednesday, there were no reports of major damage, but authorities warned residents to stay inside and not drive down flooded roads. "It's extremely dangerous," said Buzz Weiss, a spokesman for the Georgia Emergency Management Agency. He added there was a "lot of widespread localized flooding" from the rains. In Talladega County, in eastern Alabama, a tornado touched down near the Talladega Superspeedway, but did not hit the famed race track. Sheriff Jerry Studdard said they had "some trees blown down" and "a lot of power lines down," but the county escaped major damage. In Chattanooga, Tennessee, authorities there were battling to keep the Tennessee River from rising any further. The river has already reached its highest levels in 30 years, flooding a riverside park that has been a hallmark of the city's renovations in recent years. The Tennessee Valley Authority estimated as much as $7 million worth of damage so far in the area. Three-hundred structures, including dozens of homes, have been affected, the TVA said. The area received as much as eight inches in less than a day, swelling the creeks and tributaries that feed into the Tennessee river. A hospital in the community of East Ridge, Tennessee, near the Georgia border, was "surrounded 360 degrees by water," said Don Allen, the director of emergency services in Hamilton County. Ambulances can no longer get to the hospital, and authorities have routed any emergencies there to other medical facilities. In the Midwest, forecasters said eastern Kansas, western Missouri and northern Arkansas should brace for the likelihood of more tornadoes Thursday as a low-pressure system moves up from the southwest, mixing a lot of heat and moisture in the atmosphere. "If you're in that area, stay tuned," said Jeff Evans, lead forecaster with the National Weather Service's Storm Prediction Center. If the forecasts pan out, it would add to what has already been one of the busiest tornado weeks on record. Missouri junior high collapses A powerful storm hit the town of De Soto, Missouri, Tuesday night, causing part of a junior high school to collapse, bringing down trees and power lines and creating a flood of water down Main Street, officials and residents said. (Full story) No injuries or deaths were reported after the storm, and the town of 6,400 missed a second storm predicted to hit the area around midnight. The town's residents have now experienced four twisters in the past four years. Heavy rains and storms were not confined to the lower Midwest and the Southeast, however. Flooding in Holly Township, Michigan, about 50 miles northwest of Detroit, caused a 22-car freight train to derail, and several railcars were on their sides, Michigan state police reported Wednesday. The CSX train was carrying auto parts and completed vehicles. Some cars carrying propane stayed on the rails. The only environmental cleanup involved diesel fuel. A conductor and an engineer were treated for minor injuries. | X30: https://web.archive.org/web/20260620004551/https://www.cnn.com/2003/WEATHER/05/07/tornadoes/index.html | Y30: found | Z30: 603 | AA30: cnn.com | AB30: -6.27 | AC30: -2.5 | AD30: Left-leaning
A31: 16 | B31: 6 | C31: Severe Storms/Tornadoes (May 2003) | D31: Severe Storm | E31: 20030503 | F31: 20030510 | G31: 7100.9 | H31: 4128.4 | I31: 51 | J31: NATIONAL | K31: National | L31: https://www.cnn.com/2003/WEATHER/05/05/tornadoes/index.html | M31: Death, damage reported in twisters' wake - May. 5, 2003 - CNN | N31: May 5, 2003 ... Downed power lines block access to downtown Jackson, Tennessee. Much of the storm damage appeared to be across the Kansas state line in Missouri ... | O31: Relevant | P31: 0 | Q31: C | S31: FALSE | T31: The article directly covers the May 3-5, 2003 tornado outbreak affecting Missouri, Kansas, Tennessee, and other states, matching the event metadata precisely. It contains only event reporting — impacts, casualties, damage, and response — with no discussion of climate change or other causal framing beyond standard meteorological conditions (unstable air mass, jet stream). | U31: =IF(SUMPRODUCT(--ISNUMBER(SEARCH('National Domains'!$A$2:$A$48,L31)))>0,"Yes","No") | V31: =IF(COUNTIFS(Calibration!$A:$A,A31,Calibration!$B:$B,B31)>0,"Yes","No") | W31: Death, damage reported in twisters' wake New tornado warnings issued Monday JACKSON, Tennessee (CNN) -- The death toll climbed Monday as rescuers combed through twisted wreckage and crumbled buildings after an "extremely rare" outbreak of tornadoes Sunday and early Monday killed at least 39 people in Missouri, Kansas and Tennessee. Thousands of residents from Kansas to Tennessee were without power late Monday. Many of them faced the formidable task of rebuilding homes wiped out in the storms. President Bush offered his condolences to the tornado victims at a stopover in Little Rock, Arkansas, a state that also suffered tornado damage over the weekend. "The federal government will move as quickly as we possibly can where help is needed," Bush said. "Nature is awfully tough at times. And the best we can do is to pray for those who suffered." Severe weather continued to pound parts of the nation through Monday, with tornado warnings in Michigan, Tennessee, Alabama and Mississippi in effect in the evening. The National Weather Service issued a tornado watch for northern Georgia, including the metro Atlanta area, until 3:30 a.m. A storm at the Georgia-Alabama border prompted a tornado warning for the Anniston, Alabama, area. Two twisters were reported in northeastern Mississippi shortly before 8 p.m. Monday [9 p.m. EDT]. The National Weather Service radar indicated a tornado three miles west of Paynes, Mississippi, moving eastward. Radar also indicated another twister 13 miles west of Velma moving northeast. And in northwest Tennessee, radar indicated tornadoes three miles northwest of Millsfield and four miles south of Greenfield. Sunday evening, 83 twisters were sighted in central and southeastern states, said Dick Hainje, a regional director of the Federal Emergency Management Agency. "This is a huge, huge outbreak," Hainje said Monday. "Once in a while, you'll get like two or maybe three super cells with very big tornadoes, but numbers like this are extremely rare." Officials said seven people died in Sunday night's twisters in Kansas, at least 18 in Missouri and at least 14 in Tennessee. Other people thought to be in the storm's path were reported missing. No deaths were reported in Arkansas. One northeast Kansas resident told CNN that the fast-moving tornado bearing down on her Sunday night "sounded like a huge boulder rolling down the street." City is 'almost completely gone' The tornadoes were spawned from an unstable air mass ahead of a developing storm system over the Central Plains, forming a "very potent" line between dry and moist air, Dan McCarthy of the Storm Prediction Center said. "When you get those kinds of conditions and you get a jet stream that is moving right into that area, that is exactly what we're looking for in environmental conditions that can produce a ... tornado outbreak like we had yesterday," McCarthy added. There are two major tornado seasons in the Midwest and South -- spring and fall. The spring season lasts until about June. Kansas and Missouri are among the most tornado-prone states. Lawrence County in southwest Missouri was severely hit Sunday. Pierce City, a town of 1,400, looked like a war zone after a tornado spent 30 minutes gutting it. "It's not even recognizable," said Missouri state Rep. Jack Goodman. "There's not one building that hasn't been significantly damaged. Many of them are gone entirely, and very few -- if any -- will be salvageable." Councilman Thomas Majors -- who said he heard a loud hum before the storm -- said residents were suffering "total shock." Many of the town's buildings were 200 years old. "It pretty much took the tops off everything," he said. Statewide emergency declared in Missouri Missouri Gov. Bob Holden declared a statewide emergency, and said he asked Bush to declare 39 of the state's 120 counties federal disaster areas. "We're finding devastation throughout the western part of the state. My folks are telling me it's the most widespread series of tornadoes in the history of this state. "It's very widespread from southwest Missouri all the way over to north Kansas City," he said. Holden said the Red Cross, Salvation Army, and 175 National Guardsmen were working to help in the aftermath. The storms moved east through Arkansas and into Tennessee, leaving a swath of destruction, deaths and injuries. "It's like downtown Baghdad," lawyer Joe Byrd told The Associated Press after he and his law clerk emerged from the basement after a twister ripped through Jackson, Tennessee. Weather Service officials will not know the category of the storms until they do a site survey, said Ryan Jewell, a meteorologist with the National Weather Service. F-3 tornadoes have winds of between 158 and 206 mph and are capable of severe damage, with roofs and some walls torn off well-constructed houses, and most trees uprooted. F-5 is the highest on the scale. (Fujita scale) Missouri Much of the storm damage appeared to be across the Kansas state line in Missouri, where severe storm damage was reported in 16 counties, according to Jim Charrier with the Missouri Emergency Management Agency. • Missouri emergency officials reported deaths in Barton, Christian, Jasper and Cedar counties. In Stockton, the seat of Cedar County, the courthouse sustained major damage, said Jim Wakeman, operations chief of the state emergency management agency. A fire station in Battlefield, just south of Springfield, was destroyed, Wakeman said. • Dallas County's emergency management director said the northern part of his county bore the brunt of the storm, with 10 people injured and several homes destroyed. "We've got power lines down, a couple of propane tanks punctured, so we've got propane leaking into the area," said director Terry Lane. "All the major roads [into Dallas County] are blocked by debris and power lines and cars on their roofs." Kansas Gov. Kathleen Sebelius declared a state of emergency for southeastern Kansas, where the storm caused major damage in the counties of Lawrence, Crawford and Cherokee. • Deaths were reported by Kansas emergency officials in Crawford and Wyandotte counties. In Wyandotte, an 81-year-old man was killed when he was struck in the head by debris, said Don Denney, a spokesman with the unified government of Wyandotte County-Kansas City, Kansas. • Another 21 people were injured in the city and county, he said, but "it's a miracle" that the toll wasn't higher. "We've sustained significant damage in the northwest section of our city," Denney said. "Dozens and dozens of homes have been leveled and scores of others have been significantly damaged." Pat Atkins, with the Leavenworth County Emergency Management Office, said nine homes were destroyed, eight had significant damage and 30 suffered some damage. Two people were injured. According to Atkins, most of the storm damage occurred between Linwood and Basehor. Tennessee The storm also rumbled into western Tennessee, where tornadoes damaged houses, trailers and buildings. At least 11 people died in Jackson, Tennessee, according to Mayor Charles Farmer. A tornado slammed into the Madison County law enforcement center in Jackson, according to Tennessee Emergency Management spokesman Kurt Pickering. • The tornado destroyed 16 homes and damaged as many as 100, including at least 70 in east Jackson. The Red Cross is housing about 140 people in shelters in Jackson; another shelter is open in Lexington, about 28 miles east of the city, Red Cross spokeswoman Wanda Stansill said. • Authorities are working to get two water plants working in Jackson, and Madison County residents have been ordered to boil their water before drinking to kill any bacteria until further notice. Arkansas A tornado cut through the northeast part of the state, damaging homes and buildings. One serious injury was reported, officials in the area said. • In Woodruff County, the storm caused "a lot of structural damage," but the full extent of damage is not yet known, according to the sheriff's department. • One serious injury was reported in the White County town of El Paso, about 25 miles north of Little Rock, according to Arkansas Emergency Management Agency spokeswoman Jennifer Gordon. | X31: https://web.archive.org/web/20260620004726/https://www.cnn.com/2003/WEATHER/05/05/tornadoes/index.html | Y31: found | Z31: 1325 | AA31: cnn.com | AB31: -6.27 | AC31: -2.5 | AD31: Left-leaning
A32: 19 | B32: 1 | C32: Hurricane Isabel (September 2003) | D32: Tropical Cyclone | E32: 20030918 | F32: 20030919 | G32: 9322.9 | H32: 5484 | I32: 55 | J32: DC,DE,MD,NC,NJ,NY,PA,VA,WV | K32: 1,2,3,4,5,6,National | L32: https://www.npr.org/2003/09/18/1435416/hurricane-isabel-makes-u-s-landfall | M32: Hurricane Isabel Makes U.S. Landfall - NPR | N32: Hurricane Isabel Makes U.S. Landfall. September 18, 200312:00 AM ET. Heard on Day to Day. By. Alex Chadwick. ,. Brian Naylor. Hurricane Isabel Makes U.S. ... | U32: =IF(SUMPRODUCT(--ISNUMBER(SEARCH('National Domains'!$A$2:$A$48,L32)))>0,"Yes","No") | V32: =IF(COUNTIFS(Calibration!$A:$A,A32,Calibration!$B:$B,B32)>0,"Yes","No") | X32: https://web.archive.org/web/20260620004830/https://www.npr.org/2003/09/18/1435416/hurricane-isabel-makes-u-s-landfall | Y32: failed | AA32: npr.org | AB32: -4.34 | AC32: -2.5 | AD32: Left-leaning
A33: 19 | B33: 2 | C33: Hurricane Isabel (September 2003) | D33: Tropical Cyclone | E33: 20030918 | F33: 20030919 | G33: 9322.9 | H33: 5484 | I33: 55 | J33: DC,DE,MD,NC,NJ,NY,PA,VA,WV | K33: 1,2,3,4,5,6,National | L33: https://edition.cnn.com/2003/WEATHER/09/18/isabel.environment/index.html | M33: Isabel may save costliest twist for last - Sep. 19, 2003 - CNN | N33: Sep 19, 2003 ... Hurricane Isabel promises to be no exception. Although the storm system was not one of the strongest hurricanes as it smashed onto the U.S. ... | O33: Relevant | P33: 0 | Q33: C | S33: FALSE | T33: The article is directly about Hurricane Isabel making landfall on the North Carolina coast on September 18, 2003, covering storm surge impacts, inland flooding risks, and environmental damage — matching the event metadata exactly. There is no mention of climate change, global warming, or any causal attribution beyond the immediate meteorological mechanics of the storm. | U33: =IF(SUMPRODUCT(--ISNUMBER(SEARCH('National Domains'!$A$2:$A$48,L33)))>0,"Yes","No") | V33: =IF(COUNTIFS(Calibration!$A:$A,A33,Calibration!$B:$B,B33)>0,"Yes","No") | W33: Isabel may save costliest twist for last By Richard Stenger CNN (CNN) -- With punishing winds, surging waves and sheets of rain, hurricanes bring with them a powerful punch that can wreak serious environmental damage. Hurricane Isabel promises to be no exception. Although the storm system was not one of the strongest hurricanes as it smashed onto the U.S. Atlantic coast, a combination of factors suggest that it could prove to be a devastating one nonetheless. Much environmental havoc will of course be concentrated around where Isabel made landfall Thursday on the North Carolina coast. The most serious consequences may not occur until later, however, as flooding many miles inland often causes the most deaths, according to hurricane experts. The colossal physical forces at work when major tropical storms strike the coast are obvious. They can strip beaches of sand, exposing underlying rock, obliterate dunes and create new ones farther inland, and even split barrier islands in half. The major culprit is storm surges, huge waves that form due to heavy winds and low atmospheric pressure. During the most powerful hurricanes, the combination creates waves up to 15 feet (4.6 meters) higher than normal. "Storm surges can pose lots of problems for houses right along the coast. The winds may not destroy the homes, but sometimes the storm surge can. Sometimes they even go up and over houses," said Phil Klotzbach, a hurricane researcher at Colorado State University in Fort Collins. Hurricanes are ranked 1 to 5 on what is known as the Saffir-Simpson scale of strength, with 5 being the most powerful. Isabel, a Category 2 hurricane, hit North Carolina's Outer Banks early Thursday afternoon shortly before high tide, packing more of a storm surge punch. A surge could temporarily push the sea level up to 8 feet (2.4 meters) above normal in North Carolina and some neighboring states, according to meteorologists. An area at particular risk is the Chesapeake Bay, which borders some of the most densely populated regions in the Eastern United States. "Even though the center of the hurricane is not going over it, the winds of the hurricane will drive the water of the Atlantic up the Chesapeake, which could lead to some significant flooding along the shoreline of the Chesapeake," said Jim Candor of AccuWeather, a State College, Pennsylvania-based meteorological service. The storm surge could push the water level up 3 or 4 feet (1 or 1.2 meters) as far inland as Baltimore, Maryland, Candor said. The news is grim for that part of the East Coast, which already has weathered one of the wettest years in decades. The surrounding land is saturated. Reservoirs, rivers and streams are full. The region can hardly soak up more. "If this happened last year, when we were in a drought, it'd be a much different situation," said U.S. Army Corps of Engineers spokesman Peter Shugert. While the consequences of a hurricane are immediate, some consider the aftereffects to be more of a danger, even if the storm weakens into a tropical storm while it moves over land. Clouds from such systems can dump more than a foot of rain in a span of hours over a particular area, sometimes many dozens of miles inland, with devastating results. "It's the day after the storm that we're most worried about," North Carolina Gov. Michael Easley said. "That's when we lost 24 lives to flooding [the day after Hurricane Floyd in 1999]. People driving out in what they thought was 2 or 3 inches of water ended up in a ditch 6 feet deep." Over the past three decades, inland flooding has been responsible for more than half the U.S. deaths associated with hurricanes and tropical storms, according to Ed Rappaport, deputy director of the National Hurricane Center in Miami, Florida. CNN/Money's Chris Isidore contributed to this report. | X33: http://web.archive.org/web/20221005132933/http://edition.cnn.com/2003/WEATHER/09/18/isabel.environment/index.html | Y33: found | Z33: 638 | AA33: edition.cnn.com | AD33: Unidentified
A34: 19 | B34: 3 | C34: Hurricane Isabel (September 2003) | D34: Tropical Cyclone | E34: 20030918 | F34: 20030919 | G34: 9322.9 | H34: 5484 | I34: 55 | J34: DC,DE,MD,NC,NJ,NY,PA,VA,WV | K34: 1,2,3,4,5,6,National | L34: https://www.nytimes.com/2003/09/19/nyregion/the-hurricane-hits-new-jersey-shore-thousands-lose-power-in-the-south-of-state.html | M34: THE HURRICANE HITS: NEW JERSEY SHORE; Thousands Lose ... | N34: ... Lose Power in the South of State. Share full article. By Iver Peterson. Sept. 19, 2003. Stormy weather in advance of Hurricane Isabel wheeled into the ... | O34: Relevant | P34: 0 | Q34: C | S34: FALSE | T34: The article directly covers Hurricane Isabel's impacts on New Jersey and the broader New York region on September 18-19, 2003, matching the event metadata. It is pure event reporting — power outages, flooding, emergency declarations, and public response — with no mention of climate change or any causal attribution. | U34: =IF(SUMPRODUCT(--ISNUMBER(SEARCH('National Domains'!$A$2:$A$48,L34)))>0,"Yes","No") | V34: =IF(COUNTIFS(Calibration!$A:$A,A34,Calibration!$B:$B,B34)>0,"Yes","No") | W34: Stormy weather in advance of Hurricane Isabel wheeled into the New York region tonight, leaving at least 64,000 utility customers without power, mainly in southern parts of New Jersey. As the strong winds and spitting rain swept through New Jersey and New York City, upstate New York got ready to face the weakening storm. After coming ashore in North Carolina, it set course to travel up the foothills of the Appalachians and Alleghenies to western New York, which it is expected to reach early Friday. [On Long Island, a detective drowned in Long Beach about 6 p.m. Thursday, the police said. The detective, Patrick Bradley, 42, was a 15-year veteran of the Long Beach Police Department. [The Nassau County police reported that beaches at Jones Beach and Long Beach were closed to the public.] In New Jersey, with the region's most exposed shoreline to the wind and rain, Gov. James E. McGreevey declared a state of emergency. But he said the declaration was provisional, to let him mobilize the state National Guard's 2.5-ton trucks in case they are needed to rescue people stranded on the state's barrier islands. Continue reading the main storyThe power losses tonight were caused by downed utility lines, according to Conectiv and Jersey Central Power and Light. At the New Jersey State Police emergency center, Lt. Al DellaFave, the state police spokesman, said forecasters who had predicted three to five inches of rain for the state had revised their estimates downward by midafternoon, to two to four inches. ''For most of the state, things are going pretty well, but we're not expecting the worst of the storm until high tide early Friday,'' Lieutenant DellaFave said. ''We got through the first one this afternoon pretty well, and if we get through the next one, then there is definitely not going to be a problem.'' Up and down the region, the arrival of Isabel after a week's warning by forecasters was often attended by more curiosity than fear. Here at the southern tip of the state, where Cape May juts into the Atlantic, the beach roads were jammed with sightseers marveling at the breakers, measured by county officials at 10 to 15 feet in height. Boys played in the surf with stubby boogie boards, and a couple shot down the sidewalk on skateboards, propelled by bedsheets held out as sails. At Atlantic City, 47 miles up the coast from here, leaders from the Miss America pageant were putting a pretty face on the storm that has threatened, but not yet forced, the cancellation of Friday's traditional contestants' parade on the Boardwalk, which is scheduled for 6 p.m. ''It's on,'' said George Bauer, president and chief executive of the Miss America Organization. ''However, we are going to reassess at 8 a.m. Actually, I don't believe it's ever been canceled for weather.'' The weather did, however, delay flights at the region's major airports, and forced several schools to close early today and to contemplate closing Friday. Atlantic City's casinos reported some cancellations. Throughout the state, officials said that flooding was the principal danger from the storm, particularly since much of the ground was saturated with days of rain earlier in the week. Lenora Boninfante, communications director for Cape May County, said this afternoon that high waves and a slanting onshore wind had pushed seawater across oceanfront roads in Avalon. On most of the beaches, the waves drove pools of water up to the inland dunes, and Ms. Boninfante said that the afternoon high tide had come in four feet higher than expected, leading county engineers to expect at least some beach erosion. For most people the storm meant preparing for the worst and hoping for a break. In Brooklyn, Sal Argano, the general manager of the Seagate Beach Club, built a high wall of sandbags in front of the clubhouse. Sandbags were also deployed in Bound Brook, N.J., the town on the Raritan River whose business district was under eight feet of water when Tropical Storm Floyd fell on the region in 1999. ''I don't think it's going to be near as bad,'' said Federico A. Llaverias outside his business, the Spice of Life Café. Still, he filled 30 sandbags as a precaution. Continue reading the main story | X34: http://web.archive.org/web/20171229070132/http://www.nytimes.com/2003/09/19/nyregion/the-hurricane-hits-new-jersey-shore-thousands-lose-power-in-the-south-of-state.html | Y34: found | Z34: 708 | AA34: nytimes.com | AB34: -8.02 | AC34: -2.5 | AD34: Left-leaning
A35: 20 | B35: 1 | C35: California Wildfires (Fall 2003) | D35: Wildfire | E35: 20030901 | F35: 20031130 | G35: 6613.7 | H35: 3890.4 | I35: 22 | J35: CA | K35: 17,18,National | L35: https://www.cnn.com/2003/US/West/10/28/california.wildfire/ | M35: California wildfires burn through 600000 acres - Oct. 29, 2003 - CNN | N35: Oct 29, 2003 ... Skip to main content. U.S.. California wildfires burn through 600,000 acres. Wind shift helps and hinders firefighters. Wednesday, October 29 ... | O35: Relevant | P35: 0 | Q35: C | S35: FALSE | T35: The article directly covers the Fall 2003 California wildfires (Cedar Fire and others), reporting on acreage burned, deaths, containment status, and emergency response. There is no mention of climate change, global warming, or any broader causal framing beyond immediate factors like Santa Ana winds, drought, arson, and an accidental signal fire. | U35: =IF(SUMPRODUCT(--ISNUMBER(SEARCH('National Domains'!$A$2:$A$48,L35)))>0,"Yes","No") | V35: =IF(COUNTIFS(Calibration!$A:$A,A35,Calibration!$B:$B,B35)>0,"Yes","No") | W35: California wildfires burn through 600,000 acres Wind shift helps and hinders firefighters (CNN) -- An 18-mile-long wall of flames -- just a fraction of the blazes scorching Southern California -- devastated the tiny mountain community of Cuyamaca on Tuesday and bore down on the Gold Rush tourist town of Julian. The so-called Cedar Fire, perhaps the state's most devastating, breached the town limits of Julian in San Diego County on Tuesday afternoon as 125 fire engines and firefighters positioned themselves around the downtown in a bid to save its historic buildings, some of which date to the 19th century. The entire community of Cuyamaca burned Tuesday, according to California Department of Forestry spokesman John Hawkins. By late afternoon, some of the buildings in Julian were lost. With 13 wildfires raging in California from Simi Valley to San Diego, the number of homes destroyed passed 1,900, the charred land totaled more than 600,000 acres and the death toll was 16, fire officials said Tuesday. Santa Ana winds, at times gusting up to 50 or 60 mph, swept down mountain canyons from the Mexican border to Simi Valley, driving the fires. The winds began to slacken Tuesday, and the fires began following the land's topography, sometimes with devastating results. The Cedar Fire climbed uphill into Cuyamaca and Julian to consume insect-riddled Eucalyptus bark made explosive by a long drought. That blaze is considered zero percent contained, meaning it has not been stopped on any front, officials said. Dying Santa Ana winds also caused a wildfire burning in Simi Valley to shift northward Tuesday, moving the enormous flames along a path toward hundreds of homes in the Stevenson Ranch community of Los Angeles County. The unexpected turn sent thousands of residents fleeing for their lives with only 15 minutes' warning as the fire's front line drew within a mile of the neighborhood, not far from the Magic Mountain theme park and about 30 miles northwest of downtown Los Angeles. Firefighters were able to keep the flames at bay. By Tuesday evening, some residents were returning. Elsewhere in Southern California, the wind change has been good news for firefighters. "These are great weather conditions from what we've been having for the last couple of days," Los Angeles County Fire Capt. Mark Kyllingstad said earlier Tuesday. "We are going to be throwing the toolbox at the fire today." Tim Turner of the California Department of Forestry said firefighters in San Diego County, where at least four fires had burned 300,000 acres, had gotten a much-needed break. "The weather's in our favor finally," he said. "We're expecting a day of calm winds, and then they'll turn to normal offshore tomorrow. That's good news for everybody." Full-fledged fight Forced from their homes during the past three days, tens of thousands of people watched and waited as firefighters battled the blazes. Twelve people have been killed by fire in San Diego County, most while trying to escape in their cars, and four people died during the weekend in San Bernardino. Two of those were elderly men who died from stress caused by the fires. (Details on deaths) At least two of the 13 fires have been blamed on arson. The San Bernardino County Sheriff's Department released a sketch Tuesday of one of two people sought on suspicion of sparking the so-called Old Fire, which has burned nearly 30,000 acres. (Arson fuels anger) The department is looking for two men in their 20s whom authorities said were seen driving a gray van Saturday morning north of the San Bernardino city limits. Witnesses saw something being thrown into the brush from the van. The Cedar Fire was started by a lost hunter who lit a signal fire, San Diego Fire Chief Jeff Bowman said Tuesday. He said the hunter did not intend the fire to spread, and that he has been detained. The U.S. Defense Department is providing military assets to fight the wildfires in California at the request of the National Interagency Fire Center. Four C-130 aircraft configured to drop water or fire-retardant chemicals have been approved to be sent to the area. Eight UH-60 helicopters equipped with water buckets from the California National Guard are deployed. Firefighters from other parts of California and at least two other states also are helping. Bush declares major disaster President Bush declared a major disaster in affected parts of California Monday, opening the way for federal funding for governments, businesses and people affected by the fires. The Federal Emergency Management Agency and the Small Business Administration made plans to open "one-stop" centers for residents and business owners to file paperwork for emergency loans allowed under the president's disaster declaration. Firefighters have been unable to bring most of the blazes to even 20 percent containment. Several fires were at zero containment. The Cedar Fire was perhaps the most devastating. After it ignited Saturday, it consumed 80,000 acres in about 10 hours, and by Tuesday morning had reached 206,000 acres, the largest fire in the state since a blaze scorched 220,000 acres of Ventura County in 1932. "A fire of this type is not usual," Turner said. "This is an epic fire for San Diego County.". CNN correspondents Brian Cabell, Frank Buckley, Jeff Flock, Miguel Marquez and Barbara Starr, and producer Stan Wilson, contributed to this report. | X35: https://web.archive.org/web/20260620005133/https://www.cnn.com/2003/US/West/10/28/california.wildfire/ | Y35: found | Z35: 883 | AA35: cnn.com | AB35: -6.27 | AC35: -2.5 | AD35: Left-leaning
